[
  {
    "id": "558709",
    "type": "link",
    "title": "ROPE",
    "posterPath": "https://lain.bgm.tv/r/400/pic/cover/l/d0/39/558709_jSj9v.jpg",
    "releaseDate": "2025-07-25",
    "mediaType": "real",
    "rating": "",
    "description": "2025年7月25日 / 八木伶音 / 八木伶音 / 樹",
    "link": "https://bgm.tv/subject/558709"
  },
  {
    "id": "558710",
    "type": "link",
    "title": "メイソウ家族",
    "posterPath": "https://lain.bgm.tv/r/400/pic/cover/l/c2/96/558710_M03QD.jpg",
    "releaseDate": "2025-08-29",
    "mediaType": "real",
    "rating": "",
    "description": "1话 /  2025年8月29日 / 熊切和嘉、金田敬 / 戸田菜穂、永野宗典、三浦理奈、高村佳偉人、秋庭悠佑、西岡奏、木村了、久保田磨希、タージン、島田珠代、真凛、板東さえか、谷村美月",
    "link": "https://bgm.tv/subject/558710"
  },
  {
    "id": "558766",
    "type": "link",
    "title": "コトコト～おいしい心と出会う旅～ 茨城編",
    "posterPath": "https://lain.bgm.tv/r/400/pic/cover/l/89/3d/558766_3f3B1.jpg",
    "releaseDate": "2025-08-24",
    "mediaType": "real",
    "rating": "",
    "description": "2025年8月24日 / 古川雄大",
    "link": "https://bgm.tv/subject/558766"
  },
  {
    "id": "294717",
    "type": "tmdb",
    "title": "写真乐园！",
    "posterPath": "https://image.tmdb.org/t/p/w500/sOQ9HxbH9iF7EgsIDxnARVmVI84.jpg",
    "releaseDate": "2025-01-01",
    "mediaType": "tv",
    "rating": "0.0",
    "description": "本剧改编自同名漫画，讲述了梦想登上杂志封面的新晋写真偶像葛木樱（北野瑠华 饰），不仅遭遇恶劣经纪人剥削，还被跟踪狂纠缠。在关键时刻，她被梦想破灭的前导演隅田忍（押田岳 饰）所救。得知樱正陷入贫困且萌生退意后，忍决心助她一圆星梦，并提议同住合租屋，展开与“本命偶像”的同居生活。然而，等待两人的却是写真界的黑暗诱惑与危机四伏的现实……一段危险又微妙的励志恋爱喜剧就此展开。",
    "link": null,
    "tmdb_id": "294717",
    "tmdb_site_id": "tv/294717",
    "tmdb_season_number": null,
    "tmdb_origin_countries": [
      "JP"
    ],
    "tmdb_source": "tmdb_api"
  },
  {
    "id": "559693",
    "type": "link",
    "title": "レイニーブルー",
    "posterPath": "https://lain.bgm.tv/r/400/pic/cover/l/92/b7/559693_MM6sD.jpg",
    "releaseDate": "2025-07-04",
    "mediaType": "real",
    "rating": "",
    "description": "1话 /  2025年7月4日 / 柳明日菜 / 柳明日菜 / 柳明日菜",
    "link": "https://bgm.tv/subject/559693"
  },
  {
    "id": "559694",
    "type": "link",
    "title": "我靠美颜稳住天下 第一季",
    "posterPath": "https://lain.bgm.tv/r/400/pic/cover/l/f4/af/559694_yd5SE.jpg",
    "releaseDate": "2025-06-01",
    "mediaType": "real",
    "rating": "",
    "description": "15话 /  2025年6月1日 / 谷江山、苏尚卿",
    "link": "https://bgm.tv/subject/559694"
  },
  {
    "id": "293439",
    "type": "tmdb",
    "title": "日本统一 东京篇",
    "posterPath": "https://image.tmdb.org/t/p/w500/wLkSFUKJJdZMIT7pnJe7F3s9XJd.jpg",
    "releaseDate": "2025-07-02",
    "mediaType": "tv",
    "rating": "0.0",
    "description": "深夜时分，一个蒙面三人组闯入富人区的一栋住宅，挑在屋主外出的时机，小心翼翼地寻找贵重物品。就在他们翻找之际，本该外出旅行的夫妻却突然返家。慌乱之下，三人急忙往停在外面的车逃去。就在此时，另一辆车恰好从附近经过……",
    "link": null,
    "tmdb_id": "293439",
    "tmdb_site_id": "tv/293439",
    "tmdb_season_number": null,
    "tmdb_origin_countries": [
      "JP"
    ],
    "tmdb_source": "tmdb_api"
  },
  {
    "id": "559707",
    "type": "link",
    "title": "田村悠人",
    "posterPath": "https://lain.bgm.tv/r/400/pic/cover/l/bb/19/559707_brLBB.jpg",
    "releaseDate": "2025-06-06",
    "mediaType": "real",
    "rating": "",
    "description": "2025年06月06日 / 辻裕之 / 山口祥行、本宮泰風",
    "link": "https://bgm.tv/subject/559707"
  },
  {
    "id": "559762",
    "type": "link",
    "title": "为了和谐而奋斗 第二季",
    "posterPath": "https://lain.bgm.tv/r/400/pic/cover/l/2b/45/559762_00g5E.jpg",
    "releaseDate": "2025-01-01",
    "mediaType": "real",
    "rating": "",
    "description": "20话 /  2025-05-21 / 张福正、孙路路",
    "link": "https://bgm.tv/subject/559762"
  },
  {
    "id": "292626",
    "type": "tmdb",
    "title": "世界上最早的春天",
    "posterPath": "https://image.tmdb.org/t/p/w500/c7VssX13WwxRVqr8IFWOThlgY0q.jpg",
    "releaseDate": "2025-06-19",
    "mediaType": "tv",
    "rating": "8.0",
    "description": "主人公漫画家晴田真帆怀有一个秘密——她一直以高中的前辈・雪嶋周遗留的漫画设定为基础进行创作。当她对十年前去世的雪嶋产生\"想归还作品\"的强烈念头时，某夜突然穿越回高中时代。带着悔恨重过校园生活的真帆，却在过去逐渐发现关于雪嶋死亡的\"某个真相\"，谜团愈发深重......",
    "link": null,
    "tmdb_id": "292626",
    "tmdb_site_id": "tv/292626",
    "tmdb_season_number": null,
    "tmdb_origin_countries": [
      "JP"
    ],
    "tmdb_source": "tmdb_api"
  },
  {
    "id": "560081",
    "type": "link",
    "title": "天国与地狱",
    "posterPath": "https://lain.bgm.tv/r/400/pic/cover/l/b5/fa/560081_e7apj.jpg",
    "releaseDate": "2025-08-22",
    "mediaType": "real",
    "rating": "",
    "description": "2025年8月22日 / Spike Lee / William Alan Fox / Denzel Washington、Jeffrey Wright",
    "link": "https://bgm.tv/subject/560081"
  },
  {
    "id": "560125",
    "type": "link",
    "title": "新观察室",
    "posterPath": "https://lain.bgm.tv/r/400/pic/cover/l/c7/ee/560125_5dDC5.jpg",
    "releaseDate": "2025-01-01",
    "mediaType": "real",
    "rating": "",
    "description": "2025-01-31 / 吃素的狮子（林佳奇）、水王（陶宇杰）、豆豆子",
    "link": "https://bgm.tv/subject/560125"
  },
  {
    "id": "560189",
    "type": "link",
    "title": "音乐作家列传Vol.1「对决！和田薰×川井宪次」",
    "posterPath": "https://lain.bgm.tv/r/400/pic/cover/l/b1/ea/560189_PcsCL.jpg",
    "releaseDate": "2025-05-03",
    "mediaType": "real",
    "rating": "",
    "description": "1话 /  2025年5月3日 / 川井憲次、和田薫、不破了三",
    "link": "https://bgm.tv/subject/560189"
  },
  {
    "id": "560253",
    "type": "link",
    "title": "藏风 第一季",
    "posterPath": "https://lain.bgm.tv/r/400/pic/cover/l/00/96/560253_7iNzf.jpg",
    "releaseDate": "2025-05-28",
    "mediaType": "real",
    "rating": "",
    "description": "14话 /  2025年5月28日 / 史泽鲲、马正阳",
    "link": "https://bgm.tv/subject/560253"
  },
  {
    "id": "560269",
    "type": "link",
    "title": "水の中で深呼吸",
    "posterPath": "https://lain.bgm.tv/r/400/pic/cover/l/50/85/560269_WDuqC.jpg",
    "releaseDate": "2025-07-25",
    "mediaType": "real",
    "rating": "",
    "description": "1话 /  2025年7月25日 / 石川瑠華",
    "link": "https://bgm.tv/subject/560269"
  },
  {
    "id": "294214",
    "type": "tmdb",
    "title": "洗涤",
    "posterPath": "https://image.tmdb.org/t/p/w500/uqZWgZR7eP1ky1mBKxRzamiCQi.jpg",
    "releaseDate": "2025-07-03",
    "mediaType": "tv",
    "rating": "0.0",
    "description": "这是一部描绘边缘人生与社会伤痕的悬疑剧，也是一场关于共情与救赎的探索。拥有“能听见死者声音”这一无用异能的男子绯山锐介（藤原丈一郎 饰）阴差阳错踏入社会阴影之中。在与非正常死亡者的对话中，他逐步揭开被忽视的真相，倾听被遗忘的灵魂，努力为死者发声。",
    "link": null,
    "tmdb_id": "294214",
    "tmdb_site_id": "tv/294214",
    "tmdb_season_number": null,
    "tmdb_origin_countries": [
      "JP"
    ],
    "tmdb_source": "tmdb_api"
  },
  {
    "id": "560550",
    "type": "link",
    "title": "鬼牌游戏3 舞台剧",
    "posterPath": "https://lain.bgm.tv/r/400/pic/cover/l/7a/76/560550_9qD9h.jpg",
    "releaseDate": "2025-11-21",
    "mediaType": "real",
    "rating": "",
    "description": "1话 /  2025年11月21日 / 西田大輔 / 西田大輔 / 本田礼生、橋本真一、梶田拓希、土屋直武、塩田康平、野口準、速川大弥、蒼木陣、矢田悠祐、谷口賢志",
    "link": "https://bgm.tv/subject/560550"
  },
  {
    "id": "281967",
    "type": "tmdb",
    "title": "拿着手术刀的猎人",
    "posterPath": "https://image.tmdb.org/t/p/w500/5BUAbSQl87jNu1XtuP9dnpPF4fd.jpg",
    "releaseDate": "2025-01-01",
    "mediaType": "tv",
    "rating": "6.8",
    "description": "改编自小说家崔伊道的同名人气作品！故事结合犯罪、心理、悬疑与家庭创伤。 天才法医亲自追捕杀人犯父亲的惊悚韩剧 在解剖台上的一具尸体中，法医势贤发现了熟悉的杀人手法——这正是20年前被称为「裁缝师」的连环杀手、也就是她父亲的犯案风格。原以为早已死亡的父亲，如今再次现身。若不想成为猎物，就必须抢在刑警政贤之前找到他。究竟，是势贤先出手狩猎，还是成为猎杀的对象？",
    "link": null,
    "tmdb_id": "281967",
    "tmdb_site_id": "tv/281967",
    "tmdb_season_number": null,
    "tmdb_origin_countries": [
      "KR"
    ],
    "tmdb_source": "tmdb_api"
  },
  {
    "id": "560644",
    "type": "link",
    "title": "「チェリまほ The Musical」 ～30歳まで童貞だと魔法使いになれるらしい～",
    "posterPath": "https://lain.bgm.tv/r/400/pic/cover/l/44/74/560644_jcnwk.jpg",
    "releaseDate": "2025-04-11",
    "mediaType": "real",
    "rating": "",
    "description": "2025年4月11日 / 川尻恵太 / 川尻恵太 / 松田凌、荒牧慶彦",
    "link": "https://bgm.tv/subject/560644"
  },
  {
    "id": "293430",
    "type": "tmdb",
    "title": "恋爱禁止",
    "posterPath": "https://image.tmdb.org/t/p/w500/14xDH1SvBl6qvjDIcoK3eFScV3J.jpg",
    "releaseDate": "2025-07-03",
    "mediaType": "tv",
    "rating": "0.0",
    "description": "本剧改编自同名小说，讲述了不动产公司职员木村瑞帆（伊原六花 饰）与三位男性之间的纠葛：曾是精神支柱却走向家暴的前男友津坂慎也（佐藤大树 饰）、温柔体贴的现任恋人，以及因执念而盯上她的跟踪者乡田肇（渡边圭祐 饰）。三人各怀情感与秘密，将瑞帆卷入一场情与罪的漩涡。她能否逃离过去，直面真相？",
    "link": null,
    "tmdb_id": "293430",
    "tmdb_site_id": "tv/293430",
    "tmdb_season_number": null,
    "tmdb_origin_countries": [
      "JP"
    ],
    "tmdb_source": "tmdb_api"
  },
  {
    "id": "560966",
    "type": "link",
    "title": "富士山と、コーヒーと、しあわせの数式",
    "posterPath": "https://lain.bgm.tv/r/400/pic/cover/l/8e/ae/560966_iITSl.jpg",
    "releaseDate": "2025-10-24",
    "mediaType": "real",
    "rating": "",
    "description": "2025年10月24日 / 中西健二 / まなべゆきこ / 豆原一成（JO1）、市毛良枝",
    "link": "https://bgm.tv/subject/560966"
  },
  {
    "id": "560969",
    "type": "link",
    "title": "天使の集まる島",
    "posterPath": "https://lain.bgm.tv/r/400/pic/cover/l/28/13/560969_5Kd33.jpg",
    "releaseDate": "2025-08-29",
    "mediaType": "real",
    "rating": "",
    "description": "1话 /  2025年8月29日 / 堀井綾香 / 青木柚",
    "link": "https://bgm.tv/subject/560969"
  },
  {
    "id": "560980",
    "type": "link",
    "title": "ULTRAMAN MUSIC LIVE ウルトラマンゼロ15周年～Beyond the STARS～",
    "posterPath": "https://lain.bgm.tv/r/400/pic/cover/l/8a/ac/560980_ZllL8.jpg",
    "releaseDate": "2025-03-11",
    "mediaType": "real",
    "rating": "",
    "description": "1话 /  2025年3月11日 / 高見沢俊彦、宮野真守、つるの剛士、DAIGO、ボイジャー",
    "link": "https://bgm.tv/subject/560980"
  },
  {
    "id": "279082",
    "type": "tmdb",
    "title": "灵魂约定",
    "posterPath": "https://image.tmdb.org/t/p/w500/9413dPSlmHs2Xc8HKniET49gJvs.jpg",
    "releaseDate": "2025-01-01",
    "mediaType": "tv",
    "rating": "7.7",
    "description": "发生了一场意外夏茶和自己的孙子夏泽方交换灵魂，为了不让孙子的生活停摆，阿公只好顶着他的身躯继续上学，一名69岁阿公的灵魂困在一名20岁少年的身体里， 为了要把身体还给孙子的夏茶和邻居兼同学兼室友叶海渊一起行动，逐渐发现两人之间命定的关系。",
    "link": null,
    "tmdb_id": "279082",
    "tmdb_site_id": "tv/279082",
    "tmdb_season_number": null,
    "tmdb_origin_countries": [
      "TW"
    ],
    "tmdb_source": "tmdb_api"
  }
]
