[
  {
    "id": "508624",
    "type": "link",
    "title": "「政宗くんのリベンジR」～あやか・いのりのラジオは豚足の始まりリターンズ～",
    "posterPath": "https://lain.bgm.tv/r/400/pic/cover/l/86/87/508624_VXUkG.jpg",
    "releaseDate": "2023-07-02",
    "mediaType": "real",
    "rating": "",
    "description": "7话 /  2023年07月02日 / 大橋彩香、水瀬いのり",
    "link": "https://bgm.tv/subject/508624"
  },
  {
    "id": "244661",
    "type": "tmdb",
    "title": "お笑いインスパイアドラマ ラフな生活のススメ",
    "posterPath": "https://image.tmdb.org/t/p/w500/ff3EIIMUtsFZDDsrEYjScCfRqP.jpg",
    "releaseDate": "2023-01-01",
    "mediaType": "tv",
    "rating": "0.0",
    "description": "10话 /  2023-07 / 小池栄子",
    "link": null,
    "tmdb_id": "244661",
    "tmdb_site_id": "tv/244661",
    "tmdb_season_number": null,
    "tmdb_origin_countries": [
      "JP"
    ],
    "tmdb_source": "tmdb_api"
  },
  {
    "id": "459305",
    "type": "link",
    "title": "モダンかアナーキー",
    "posterPath": "https://lain.bgm.tv/r/400/pic/cover/l/2c/16/459305_W7r66.jpg",
    "releaseDate": "2023-01-01",
    "mediaType": "real",
    "rating": "",
    "description": "1话 /  2023-07-01 / 杉本大地 / 杉本大地 / 金子大地",
    "link": "https://bgm.tv/subject/459305"
  },
  {
    "id": "486759",
    "type": "link",
    "title": "按你的要求我隐婚了",
    "posterPath": "https://lain.bgm.tv/r/400/pic/cover/l/24/8d/486759_zlvbb.jpg",
    "releaseDate": "2023-01-01",
    "mediaType": "real",
    "rating": "",
    "description": "12话 /  2023-07-01 / 刘一鸣、心念",
    "link": "https://bgm.tv/subject/486759"
  },
  {
    "id": "470612",
    "type": "link",
    "title": "Shin Megami Tensei 30th LIVE: Band of Shadows Concert",
    "posterPath": "https://lain.bgm.tv/r/400/pic/cover/l/90/42/470612_E9Pu0.jpg",
    "releaseDate": "2023-01-01",
    "mediaType": "real",
    "rating": "",
    "description": "1话 /  2023-07-01",
    "link": "https://bgm.tv/subject/470612"
  },
  {
    "id": "513013",
    "type": "link",
    "title": "765 MILLIONSTARS LIVE 2023 Dreamin’ Groove",
    "posterPath": "https://lain.bgm.tv/r/400/pic/cover/l/99/37/513013_wqOQO.jpg",
    "releaseDate": "2023-07-01",
    "mediaType": "real",
    "rating": "",
    "description": "3话 /  2023年7月1日",
    "link": "https://bgm.tv/subject/513013"
  },
  {
    "id": "426645",
    "type": "link",
    "title": "断捨離パラダイス",
    "posterPath": "https://lain.bgm.tv/r/400/pic/cover/l/db/bf/426645_9oSzS.jpg",
    "releaseDate": "2023-06-30",
    "mediaType": "real",
    "rating": "",
    "description": "1话 /  2023年6月30日 / 篠田諒、武藤十夢",
    "link": "https://bgm.tv/subject/426645"
  },
  {
    "id": "131305",
    "type": "tmdb",
    "title": "绝世网红",
    "posterPath": "https://image.tmdb.org/t/p/w500/8WY3IGk4a3PzfrncHp3Y3vtkO2y.jpg",
    "releaseDate": "2023-06-30",
    "mediaType": "tv",
    "rating": "7.8",
    "description": "名气、金钱、权力。徐雅莉一夜爆红，成为社交媒体明星。但在这个浮华光鲜的网红世界，致命的后果在等待着她。",
    "link": null,
    "tmdb_id": "131305",
    "tmdb_site_id": "tv/131305",
    "tmdb_season_number": null,
    "tmdb_origin_countries": [
      "KR"
    ],
    "tmdb_source": "tmdb_api"
  },
  {
    "id": "407937",
    "type": "link",
    "title": "东京复仇者2 血之万圣节篇 -决战-",
    "posterPath": "https://lain.bgm.tv/r/400/pic/cover/l/21/c7/407937_e2aA0.jpg",
    "releaseDate": "2023-06-30",
    "mediaType": "real",
    "rating": "",
    "description": "1话 /  2023年6月30日 / 英勉 / 髙橋泉 / 北村匠海",
    "link": "https://bgm.tv/subject/407937"
  },
  {
    "id": "229776",
    "type": "tmdb",
    "title": "如果蜗牛有爱情",
    "posterPath": "https://image.tmdb.org/t/p/w500/ix3US5jAuLvQBPW656s82AM1704.jpg",
    "releaseDate": "2023-01-01",
    "mediaType": "tv",
    "rating": "7.2",
    "description": "当钝感蜗牛遇上霸道狮子，情思迟迟难以传递；当天才新人女警遇上深沉资深神探，理念碰撞火花不断，扑朔迷离的案情困局待破……",
    "link": null,
    "tmdb_id": "229776",
    "tmdb_site_id": "tv/229776",
    "tmdb_season_number": null,
    "tmdb_origin_countries": [
      "TH"
    ],
    "tmdb_source": "tmdb_api"
  },
  {
    "id": "424691",
    "type": "link",
    "title": "オレンジ・ランプ",
    "posterPath": "https://lain.bgm.tv/r/400/pic/cover/l/c0/8a/424691_FQhEa.jpg",
    "releaseDate": "2023-06-30",
    "mediaType": "real",
    "rating": "",
    "description": "2023年6月30日 / 貫地谷しほり、和田正人",
    "link": "https://bgm.tv/subject/424691"
  },
  {
    "id": "437105",
    "type": "link",
    "title": "札束と温泉",
    "posterPath": "https://lain.bgm.tv/r/400/pic/cover/l/8a/e7/437105_hW3Al.jpg",
    "releaseDate": "2023-06-30",
    "mediaType": "real",
    "rating": "",
    "description": "2023年6月30日 / 沢口愛華",
    "link": "https://bgm.tv/subject/437105"
  },
  {
    "id": "443742",
    "type": "link",
    "title": "夺宝奇兵5：命运转盘",
    "posterPath": "https://lain.bgm.tv/r/400/pic/cover/l/23/35/443742_Y0Y10.jpg",
    "releaseDate": "2023-06-30",
    "mediaType": "real",
    "rating": "6.3",
    "description": "1话 /  2023年6月30日 / James Mangold / Jez Butterworth、John-Henry Butterworth、David Koepp、James Mangold / Harrison Ford、Phoebe Waller-Bridge",
    "link": "https://bgm.tv/subject/443742"
  },
  {
    "id": "346054",
    "type": "link",
    "title": "战士 第三季",
    "posterPath": "https://lain.bgm.tv/r/400/pic/cover/l/9f/0a/346054_3yLJ1.jpg",
    "releaseDate": "2023-01-01",
    "mediaType": "real",
    "rating": "",
    "description": "10话 /  2023-06-29 / Andrew Koji",
    "link": "https://bgm.tv/subject/346054"
  },
  {
    "id": "530443",
    "type": "link",
    "title": "玫瑰警告",
    "posterPath": "https://lain.bgm.tv/r/400/pic/cover/l/12/6b/530443_gA13E.jpg",
    "releaseDate": "2023-06-29",
    "mediaType": "real",
    "rating": "",
    "description": "20话 /  2023年6月29日 / 夙七烈、小K、佐恩、古奇、倒吊男、天花板、陈冠豪、煎蛋饼、夜渡于野、路扬君、petboy、水无涯、紫枫儿、李白、小苒、顾辰",
    "link": "https://bgm.tv/subject/530443"
  },
  {
    "id": "197579",
    "type": "tmdb",
    "title": "暮色心约",
    "posterPath": "https://image.tmdb.org/t/p/w500/4Y4NGiAgpQ6mUx2al2uonAEUhlH.jpg",
    "releaseDate": "2023-06-29",
    "mediaType": "tv",
    "rating": "10.0",
    "description": "从事心理健康指导工作的刘瑕路遇一名女子想要跳桥，刘瑕见状便用心理学知识进行疏导，最后成功将该女子救下。这一幕恰巧被正想将自己的心理推理小说改编成剧本的作家祁连山目睹，便力邀刘瑕当顾问。为实现帮助更多人的理想，刘瑕成立了自己的工作室，以出色的专业水准和共情能力，为因事业、家庭或情感问题感到心理压力的来访者排忧解困，帮助他们恢复健康积极的生活。祁连山的小说在改编成影视剧的过程中得到了刘瑕的专业指导。随着两人接触不断加深，他深深地被刘瑕所吸引。刘瑕工作之余，与天才极客沈钦合作开发了AI心理测试系统，并将之应用于儿童及社区公益，效果极佳。祁连山也逐渐参与到刘瑕的公益事业中，一起帮助那些面临生活挑战的人走出心理困境。二人在一次次携手合作中越走越近，最终在各自事业都取得成功的同时，也收获了美好的爱情。",
    "link": null,
    "tmdb_id": "197579",
    "tmdb_site_id": "tv/197579",
    "tmdb_season_number": null,
    "tmdb_origin_countries": [
      "CN"
    ],
    "tmdb_source": "tmdb_api"
  },
  {
    "id": "362850",
    "type": "link",
    "title": "猎魔人 第三季",
    "posterPath": "https://lain.bgm.tv/r/400/pic/cover/l/de/b9/362850_4x5Dd.jpg",
    "releaseDate": "2023-06-29",
    "mediaType": "real",
    "rating": "6.1",
    "description": "8话 /  2023年6月29日",
    "link": "https://bgm.tv/subject/362850"
  },
  {
    "id": "229579",
    "type": "tmdb",
    "title": "追光的日子",
    "posterPath": "https://image.tmdb.org/t/p/w500/bH8fVy3msdoSjTz23Y9g0cFKBJM.jpg",
    "releaseDate": "2023-01-01",
    "mediaType": "tv",
    "rating": "8.0",
    "description": "离开教育行业五年的郝楠，在经营店铺失败后，重回教师岗位。十八岁的任真因不靠谱的父亲导致高考落榜，在天台遇到了同样失意的郝楠，然而郝楠却用自己的亲身经历鼓励了任真。巧合的是，成为青云中学高三14班班主任的郝楠与新入班的任真再度相遇。在随后备战高考的日子里，郝楠与班里的学生从互相不理解到惺惺相惜，在他的努力下，这群憧憬未来的少年逐渐敞开心扉，开始信任这位特殊的老师。郝楠了解到每个学生的梦想和想要实现的人生价值，他如同麦田里的守望者，守护着一个个心怀梦想的少年，让他们积极为未来奋战，以饱满的状态应对高考，迎接各自的灿烂人生。",
    "link": null,
    "tmdb_id": "229579",
    "tmdb_site_id": "tv/229579",
    "tmdb_season_number": null,
    "tmdb_origin_countries": [
      "CN"
    ],
    "tmdb_source": "tmdb_api"
  },
  {
    "id": "435193",
    "type": "link",
    "title": "量产型璃子 另一位模型女子的人生组装记",
    "posterPath": "https://lain.bgm.tv/r/400/pic/cover/l/01/e6/435193_lrSrl.jpg",
    "releaseDate": "2023-01-01",
    "mediaType": "real",
    "rating": "6.7",
    "description": "10话 /  2023-06-29 / 三石直和、ヤングポール / マンボウやしろ、畑中翔太、オコチャ、山元悠加 / 与田祐希",
    "link": "https://bgm.tv/subject/435193"
  },
  {
    "id": "442602",
    "type": "link",
    "title": "あなたがしてくれなくても 特別編",
    "posterPath": null,
    "releaseDate": "2023-06-29",
    "mediaType": "real",
    "rating": "",
    "description": "1话 /  2023年6月29日 / 奈緒、岩田剛典（EXILE / 三代目 J SOUL BROTHERS from EXILE TRIBE）、田中みな実、永山瑛太、武田玲奈、さとうほなみ、宇野祥平、MEGUMI、大塚寧々、野間口徹",
    "link": "https://bgm.tv/subject/442602"
  },
  {
    "id": "218994",
    "type": "tmdb",
    "title": "删除",
    "posterPath": "https://image.tmdb.org/t/p/w500/bTcIV7RfuFPDTdqmZApLjEs7STv.jpg",
    "releaseDate": "2023-01-01",
    "mediaType": "tv",
    "rating": "6.8",
    "description": "一对婚外情恋人发现了一部让可以他人消失不见的手机，于是他们开始规划两人的新生活。",
    "link": null,
    "tmdb_id": "218994",
    "tmdb_site_id": "tv/218994",
    "tmdb_season_number": null,
    "tmdb_origin_countries": [
      "TH"
    ],
    "tmdb_source": "tmdb_api"
  },
  {
    "id": "229553",
    "type": "tmdb",
    "title": "与你十年，予我半生",
    "posterPath": "https://image.tmdb.org/t/p/w500/qk9uXn9787p1FNR1UyLJ5FTqhND.jpg",
    "releaseDate": "2023-01-01",
    "mediaType": "tv",
    "rating": "5.0",
    "description": "寒门贵子林亦诚（张耀饰）、高智商美女王燃（张雅钦饰）、最后的“古惑仔”陈涛（袁家欢饰）、“海王”阔少李哲凯（文力饰）、乖乖女刘珂（赵星卉饰）五个成长背景以及性格截然不同的年轻人，从相知相识到隔阂分裂，再到重塑如初。他们直面情感痛点与生活困境，在一系列或感动或曲折的故事中，串联起最动人闪耀的青春模样。",
    "link": null,
    "tmdb_id": "229553",
    "tmdb_site_id": "tv/229553",
    "tmdb_season_number": null,
    "tmdb_origin_countries": [
      "CN"
    ],
    "tmdb_source": "tmdb_api"
  },
  {
    "id": "198102",
    "type": "tmdb",
    "title": "历劫惊途",
    "posterPath": "https://image.tmdb.org/t/p/w500/h8Y9FDPIk1aHDpTbPoLLu7jnxid.jpg",
    "releaseDate": "2023-01-01",
    "mediaType": "tv",
    "rating": "7.5",
    "description": "在挟持者夺取控制权后，谈判专家山姆·尼尔森面临人生中最惊险的挑战，所有乘客亦深陷其中。为了扭转局势，他将施展所有谈判手段，而情况亦越来越严峻。",
    "link": null,
    "tmdb_id": "198102",
    "tmdb_site_id": "tv/198102",
    "tmdb_season_number": null,
    "tmdb_origin_countries": [
      "GB"
    ],
    "tmdb_source": "tmdb_api"
  },
  {
    "id": "487652",
    "type": "link",
    "title": "两A相逢必有一O 第二季",
    "posterPath": "https://lain.bgm.tv/r/400/pic/cover/l/dd/6b/487652_MJddX.jpg",
    "releaseDate": "2023-01-01",
    "mediaType": "real",
    "rating": "",
    "description": "12话 /  2023-06-27 / 张福正、孙路路",
    "link": "https://bgm.tv/subject/487652"
  }
]
