[
  {
    "id": "292626",
    "type": "tmdb",
    "title": "世界上最早的春天",
    "posterPath": "https://image.tmdb.org/t/p/w500/c7VssX13WwxRVqr8IFWOThlgY0q.jpg",
    "releaseDate": "2025-06-19",
    "mediaType": "tv",
    "rating": "8.0",
    "description": "主人公漫画家晴田真帆怀有一个秘密——她一直以高中的前辈・雪嶋周遗留的漫画设定为基础进行创作。当她对十年前去世的雪嶋产生\"想归还作品\"的强烈念头时，某夜突然穿越回高中时代。带着悔恨重过校园生活的真帆，却在过去逐渐发现关于雪嶋死亡的\"某个真相\"，谜团愈发深重......",
    "link": null,
    "tmdb_id": "292626",
    "tmdb_site_id": "tv/292626",
    "tmdb_season_number": null,
    "tmdb_origin_countries": [
      "JP"
    ],
    "tmdb_source": "tmdb_api"
  },
  {
    "id": "255483",
    "type": "tmdb",
    "title": "焕羽",
    "posterPath": "https://image.tmdb.org/t/p/w500/yC6mru4KDYpkgbGYWABzVowDgKI.jpg",
    "releaseDate": "2025-06-19",
    "mediaType": "tv",
    "rating": "7.6",
    "description": "2007年，十六岁的少女乔青羽一家因姐姐乔贝羽的死因饱受流言折磨，不得已举家从小县城顺云搬迁到省会寰州。为了尽快恢复一家人的正常生活，青羽在同学明盛的帮助下，寻找姐姐去世的真实原因。随着真相逐渐显露，青羽惊诧于白羽承受的不公，决心帮她讨回公道。青羽在表哥婚礼上大闹，她的行为并没有让事情变好，反而让爷爷憎恶她，也让母亲情绪越发崩溃。在青羽最无助的时候，明盛默默地陪伴着她，坚定不移地相信她，鼓励她要坚持做自己想做的事情，学姐王沐沐用舞蹈帮助她重新振作。青羽主动缓和与家人之间的关系，学习和生活都在逐渐好起来，最终考上了自己心仪的大学。四年后，大学毕业的青羽与明盛收获了甜蜜的爱情。",
    "link": null,
    "tmdb_id": "255483",
    "tmdb_site_id": "tv/255483",
    "tmdb_season_number": null,
    "tmdb_origin_countries": [
      "CN"
    ],
    "tmdb_source": "tmdb_api"
  },
  {
    "id": "230775",
    "type": "tmdb",
    "title": "竞选伙伴",
    "posterPath": "https://image.tmdb.org/t/p/w500/eAywirQi3wk80tTjoPiNxdBgbhB.jpg",
    "releaseDate": "2025-01-01",
    "mediaType": "tv",
    "rating": "8.3",
    "description": "该剧讲述因意外事件而成为全校笑柄的卢世勋（尹贤秀饰），在学生会会长选举中被提名为副会长候选人，并通过各种阴谋赢得选举的青少年政治剧",
    "link": null,
    "tmdb_id": "230775",
    "tmdb_site_id": "tv/230775",
    "tmdb_season_number": null,
    "tmdb_origin_countries": [
      "KR"
    ],
    "tmdb_source": "tmdb_api"
  },
  {
    "id": "233969",
    "type": "tmdb",
    "title": "淬火年代",
    "posterPath": "https://image.tmdb.org/t/p/w500/6UBQRdfsXmygtAn4l9NC93bVrN6.jpg",
    "releaseDate": "2025-06-18",
    "mediaType": "tv",
    "rating": "9.0",
    "description": "上世纪九十年代末，留学德国的柳钧回到家乡东海，他顺应时代发展，立志将父亲的老机械制造厂改造成科技领先的现代化制造厂。民企在技术、资金、人脉等各方面都遇到重重困难，举步维艰，但好友钱宏明的进出口贸易、房地产等事业却搞得风生水起，二人互相帮助互相提醒。柳钧因技术结识了杨巡，后又因为技术与杨巡闹翻，结下冤仇，好在当地东海集团负责人宋运辉对他青睐有加，在腾飞厂的发展中给予了有力支持。柳钧脚踏实地，一面适应、融入国内环境，探索经营管理之道，一面攻破技术壁垒，最终凭借过硬的技术和一腔理想主义，渡过生存难关，完成了腾飞厂一次又一次的转型升级。柳钧实现了自己的价值，腾飞厂也在中国制造业的洪流中奋勇争先，占据了一席之地。",
    "link": null,
    "tmdb_id": "233969",
    "tmdb_site_id": "tv/233969",
    "tmdb_season_number": null,
    "tmdb_origin_countries": [
      "CN"
    ],
    "tmdb_source": "tmdb_api"
  },
  {
    "id": "261668",
    "type": "tmdb",
    "title": "异轨姝途",
    "posterPath": "https://image.tmdb.org/t/p/w500/eRIzK09lEfYFkmAEE1sUjFlnyoB.jpg",
    "releaseDate": "2025-01-01",
    "mediaType": "tv",
    "rating": "7.0",
    "description": "本剧改编自Mary S. Lovell传记小说《Mitford家的姐妹们》。\n\n原本应该墨守成规一到年纪就钓个金龟婿过上锦衣玉食生活的贵族姐妹，在动荡的时局中，走向了不同的人生轨道。她们之中，有法西斯，有共产党；有作家，有农场专家；有情妇，也有公爵夫人。丑闻不过是她们绕身的装饰品，离经叛道不过是她们最浅显的标签。她们撕下世俗强加的华丽假面，用各自的人生选择在历史的画布上肆意泼墨，墨迹交织，最终勾勒出的，是一个旧秩序摇摇欲坠时，个体在信仰与私欲、坚守与迷失中挣扎的群像，真实映照出时代褶皱里人性的多棱与混沌。【炸鱼薯条字幕组原创简介】",
    "link": null,
    "tmdb_id": "261668",
    "tmdb_site_id": "tv/261668",
    "tmdb_season_number": null,
    "tmdb_origin_countries": [
      "GB"
    ],
    "tmdb_source": "tmdb_api"
  },
  {
    "id": "564952",
    "type": "link",
    "title": "合法丈夫解冻指南",
    "posterPath": "https://lain.bgm.tv/r/400/pic/cover/l/11/22/564952_K99K2.jpg",
    "releaseDate": "2025-06-17",
    "mediaType": "real",
    "rating": "",
    "description": "20话 /  2025年6月17日 / 倔强的小红、6熙",
    "link": "https://bgm.tv/subject/564952"
  },
  {
    "id": "288163",
    "type": "tmdb",
    "title": "蓝天啤酒",
    "posterPath": "https://image.tmdb.org/t/p/w500/9RmQthkiBSt5Nnaz2JitLkRXPLQ.jpg",
    "releaseDate": "2025-06-16",
    "mediaType": "tv",
    "rating": "0.0",
    "description": "本剧主角森川行男（22岁）是自称“末流大学”文学系四年级学生，信奉“人生的丰盈取决于在自然中、蓝天下畅饮冰镇啤酒的次数”，成日沉浸户外生活的自由人。某日，正为求职焦头烂额的同级生八木拓马（22岁）找上门来。森川以“求职成功需在学生时代完成某项壮举”为由说服八木，提议两人乘着“安全套制造商开发的橡皮艇”从河流上游划至入海口。他们还拉上好友学弟松宫一朗太（22岁），三人在千叶深山的河滩搭帐篷、炸溪蟹充饥，展开野趣十足的露营。次日清晨，三人拼死完成漂流后成就感爆棚，自此每周找借口开启新冒险：为节省生活费挑战“纯靠自然食材生存的省钱露营”、堆砌天然石块享受“露天温泉露营”、讲究格调的“时尚露营”……甚至吸引向往户外生活的女学生三条弥生（21岁）加入，闹剧不断。旅途中更频频遭遇怪人——如总爱显摆的冷酷模特级独行露营者大山千晶。四名大学生在一次次奇遇中，逐渐勾勒出各自的未来图景。",
    "link": null,
    "tmdb_id": "288163",
    "tmdb_site_id": "tv/288163",
    "tmdb_season_number": null,
    "tmdb_origin_countries": [
      "JP"
    ],
    "tmdb_source": "tmdb_api"
  },
  {
    "id": "281967",
    "type": "tmdb",
    "title": "拿着手术刀的猎人",
    "posterPath": "https://image.tmdb.org/t/p/w500/5BUAbSQl87jNu1XtuP9dnpPF4fd.jpg",
    "releaseDate": "2025-01-01",
    "mediaType": "tv",
    "rating": "6.8",
    "description": "改编自小说家崔伊道的同名人气作品！故事结合犯罪、心理、悬疑与家庭创伤。 天才法医亲自追捕杀人犯父亲的惊悚韩剧 在解剖台上的一具尸体中，法医势贤发现了熟悉的杀人手法——这正是20年前被称为「裁缝师」的连环杀手、也就是她父亲的犯案风格。原以为早已死亡的父亲，如今再次现身。若不想成为猎物，就必须抢在刑警政贤之前找到他。究竟，是势贤先出手狩猎，还是成为猎杀的对象？",
    "link": null,
    "tmdb_id": "281967",
    "tmdb_site_id": "tv/281967",
    "tmdb_season_number": null,
    "tmdb_origin_countries": [
      "KR"
    ],
    "tmdb_source": "tmdb_api"
  },
  {
    "id": "292035",
    "type": "tmdb",
    "title": "逆爱",
    "posterPath": "https://image.tmdb.org/t/p/w500/qXB8wIuRQ4boWSZSoLFAu5g6K9l.jpg",
    "releaseDate": "2025-06-16",
    "mediaType": "tv",
    "rating": "8.3",
    "description": "原本只是为了报复前女友，没想到撩着撩着，自己先沦陷。落魄直男吴所畏为了出气，决定把她的现任男友池骋给「撩」过来。结果这位跩跩的公子哥不但上钩，还让吴所畏自己也弯得彻底！两人从互看不顺眼，到一路暧昧，误会、偶遇、床边纠缠通通来，从情敌变情人，甜到发烫。就在感情越陷越深的时候，前任回国、秘密曝光、身份翻转——这段恋情，还有没有未来？",
    "link": null,
    "tmdb_id": "292035",
    "tmdb_site_id": "tv/292035",
    "tmdb_season_number": null,
    "tmdb_origin_countries": [
      "CN"
    ],
    "tmdb_source": "tmdb_api"
  },
  {
    "id": "567207",
    "type": "link",
    "title": "Roselia「Sei stark」",
    "posterPath": "https://lain.bgm.tv/r/400/pic/cover/l/90/30/567207_sp666.jpg",
    "releaseDate": "2025-01-01",
    "mediaType": "real",
    "rating": "",
    "description": "2025-06-15 / Roselia、夢限大みゅーたいぷ（オープニングアクト）",
    "link": "https://bgm.tv/subject/567207"
  },
  {
    "id": "613054",
    "type": "link",
    "title": "世界计划交响乐2025",
    "posterPath": "https://lain.bgm.tv/r/400/pic/cover/l/9d/f4/613054_hsKWM.jpg",
    "releaseDate": "2025-01-01",
    "mediaType": "real",
    "rating": "",
    "description": "4话 /  2025-06-15 / 東京フィルハーモニー交響楽団、大阪交響楽団、セカイシンフォニースペシャルバンド、栗田博文（指揮者）",
    "link": "https://bgm.tv/subject/613054"
  },
  {
    "id": "578628",
    "type": "link",
    "title": "Anisong女子部2025\"Return~集结！\"动漫歌曲演唱会",
    "posterPath": "https://lain.bgm.tv/r/400/pic/cover/l/5a/4e/578628_kGMaM.jpg",
    "releaseDate": "2025-01-01",
    "mediaType": "real",
    "rating": "",
    "description": "2话 /  2025-06-14 / 堀江美都子、米倉千尋、松澤由実",
    "link": "https://bgm.tv/subject/578628"
  },
  {
    "id": "541512",
    "type": "link",
    "title": "RAISE A SUILEN LIVE 2025",
    "posterPath": "https://lain.bgm.tv/r/400/pic/cover/l/71/44/541512_ULDc6.jpg",
    "releaseDate": "2025-01-01",
    "mediaType": "real",
    "rating": "",
    "description": "2025-06-14 / RAISE A SUILEN",
    "link": "https://bgm.tv/subject/541512"
  },
  {
    "id": "527944",
    "type": "link",
    "title": "木の上の軍隊",
    "posterPath": "https://lain.bgm.tv/r/400/pic/cover/l/85/72/527944_x454f.jpg",
    "releaseDate": "2025-01-01",
    "mediaType": "real",
    "rating": "",
    "description": "1话 /  2025-06-13 / 平一紘 / 平一紘 / 堤真一、山田裕貴",
    "link": "https://bgm.tv/subject/527944"
  },
  {
    "id": "420963",
    "type": "link",
    "title": "新·驯龙高手",
    "posterPath": "https://lain.bgm.tv/r/400/pic/cover/l/71/3a/420963_d8EYd.jpg",
    "releaseDate": "2025-06-13",
    "mediaType": "real",
    "rating": "7.3",
    "description": "1话 /  2025年6月13日 / Dean DeBlois / Dean DeBlois / Mason Thames、Nico Parker",
    "link": "https://bgm.tv/subject/420963"
  },
  {
    "id": "564383",
    "type": "link",
    "title": "Loveca部 成为最强玩家之路！！",
    "posterPath": "https://lain.bgm.tv/r/400/pic/cover/l/43/d9/564383_9f9F5.jpg",
    "releaseDate": "2025-01-01",
    "mediaType": "real",
    "rating": "",
    "description": "2025-06-13 / 相良茉優、法元明菜、岬なこ、絵森彩、指出毬亜、新田恵海、坂倉花、楡井希実、櫻井陽菜",
    "link": "https://bgm.tv/subject/564383"
  },
  {
    "id": "582496",
    "type": "link",
    "title": "如月车站2",
    "posterPath": "https://lain.bgm.tv/r/400/pic/cover/l/b1/ac/582496_an1om.jpg",
    "releaseDate": "2025-01-01",
    "mediaType": "real",
    "rating": "",
    "description": "2025-06-13 / 永江二朗 / 宮本武史 / 本田望結、恒松祐里",
    "link": "https://bgm.tv/subject/582496"
  },
  {
    "id": "552577",
    "type": "link",
    "title": "KAMITSUBAKI WARS 2025 神椿後楽園戦線 KAMITSUBAKI XPERIENCE",
    "posterPath": "https://lain.bgm.tv/r/400/pic/cover/l/ad/15/552577_v7tT7.jpg",
    "releaseDate": "2025-06-13",
    "mediaType": "real",
    "rating": "",
    "description": "2话 /  2025年6月13日 / 花譜、ヰ世界情緒、幸祜、理芽、春猿火、明透、心世紀 (御莉姫、佳鏡院、硝子宮)、罪十罰 (氷夏至、 美古途、夕凪機)",
    "link": "https://bgm.tv/subject/552577"
  },
  {
    "id": "528590",
    "type": "link",
    "title": "青春ゲシュタルト崩壊",
    "posterPath": "https://lain.bgm.tv/r/400/pic/cover/l/53/7d/528590_987c0.jpg",
    "releaseDate": "2025-06-13",
    "mediaType": "real",
    "rating": "",
    "description": "2025年6月13日 / 佐藤新（IMP.）、渡邉美穂",
    "link": "https://bgm.tv/subject/528590"
  },
  {
    "id": "564463",
    "type": "link",
    "title": "mopim（ムパン）",
    "posterPath": "https://lain.bgm.tv/r/400/pic/cover/l/98/82/564463_J5oO8.jpg",
    "releaseDate": "2025-06-13",
    "mediaType": "real",
    "rating": "",
    "description": "2025年6月13日 / 水落豊 / 水落豊 / 有村架純、オダギリジョー、泉澤祐希",
    "link": "https://bgm.tv/subject/564463"
  },
  {
    "id": "534453",
    "type": "link",
    "title": "人偶之家",
    "posterPath": "https://lain.bgm.tv/r/400/pic/cover/l/bd/12/534453_AH8gY.jpg",
    "releaseDate": "2025-01-01",
    "mediaType": "real",
    "rating": "6.7",
    "description": "1话 /  2025-06-13 / 矢口史靖 / 矢口史靖 / 長澤まさみ",
    "link": "https://bgm.tv/subject/534453"
  },
  {
    "id": "564464",
    "type": "link",
    "title": "道子、未知満ちて。",
    "posterPath": "https://lain.bgm.tv/r/400/pic/cover/l/ad/97/564464_mLPeK.jpg",
    "releaseDate": "2025-06-13",
    "mediaType": "real",
    "rating": "",
    "description": "2025年6月13日 / 武井咲華 / 武井咲華 / 鳴海唯、小手伸也",
    "link": "https://bgm.tv/subject/564464"
  },
  {
    "id": "250307",
    "type": "tmdb",
    "title": "匹兹堡医护前线",
    "posterPath": "https://image.tmdb.org/t/p/w500/ohKJ1hbzPSt7AHnR7hplo6cu4sK.jpg",
    "releaseDate": "2025-06-13",
    "mediaType": "tv",
    "rating": "8.7",
    "description": "　　讲述匹兹堡一家医院的医护人员日常应对个人危机、职场政治和危重病人的情志护理等情况，检视当今美国医疗工作者所面临的挑战，揭示他们肩负崇高使命所需的韧性。",
    "link": null,
    "tmdb_id": "250307",
    "tmdb_site_id": "tv/250307",
    "tmdb_season_number": null,
    "tmdb_origin_countries": [
      "US"
    ],
    "tmdb_source": "tmdb_api"
  },
  {
    "id": "526928",
    "type": "link",
    "title": "重写",
    "posterPath": "https://lain.bgm.tv/r/400/pic/cover/l/7d/92/526928_Byv77.jpg",
    "releaseDate": "2025-06-13",
    "mediaType": "real",
    "rating": "",
    "description": "2025年6月13日 / 松居大悟 / 上田誠（ヨーロッパ企画） / 池田エライザ",
    "link": "https://bgm.tv/subject/526928"
  }
]
