[
  {
    "id": "479818",
    "type": "link",
    "title": "一触即燃",
    "posterPath": "https://lain.bgm.tv/r/400/pic/cover/l/aa/51/479818_3Z8TD.jpg",
    "releaseDate": "2024-01-01",
    "mediaType": "real",
    "rating": "",
    "description": "18话 /  2024-01-23 / 魅影之声、斑马",
    "link": "https://bgm.tv/subject/479818"
  },
  {
    "id": "479821",
    "type": "link",
    "title": "你能不能不撩我 第一季",
    "posterPath": "https://lain.bgm.tv/r/400/pic/cover/l/da/41/479821_js3kX.jpg",
    "releaseDate": "2024-01-01",
    "mediaType": "real",
    "rating": "",
    "description": "16话 /  2024-01-04 / 刘一鸣、王宁",
    "link": "https://bgm.tv/subject/479821"
  },
  {
    "id": "479826",
    "type": "link",
    "title": "暹罗三夜",
    "posterPath": "https://lain.bgm.tv/r/400/pic/cover/l/23/c1/479826_ilX1h.jpg",
    "releaseDate": "2024-01-01",
    "mediaType": "real",
    "rating": "",
    "description": "3话 /  2024-01-01 / 魅影之声、天空",
    "link": "https://bgm.tv/subject/479826"
  },
  {
    "id": "479827",
    "type": "link",
    "title": "24格的谎言",
    "posterPath": "https://lain.bgm.tv/r/400/pic/cover/l/da/54/479827_p5ufT.jpg",
    "releaseDate": "2024-01-01",
    "mediaType": "real",
    "rating": "",
    "description": "16话 /  2024-01-01 / 张福正、商桐",
    "link": "https://bgm.tv/subject/479827"
  },
  {
    "id": "479828",
    "type": "link",
    "title": "陈木",
    "posterPath": "https://lain.bgm.tv/r/400/pic/cover/l/ff/ae/479828_iVQqI.jpg",
    "releaseDate": "2024-01-04",
    "mediaType": "real",
    "rating": "",
    "description": "13话 /  2024年1月4日 / 张舸、6熙",
    "link": "https://bgm.tv/subject/479828"
  },
  {
    "id": "479829",
    "type": "link",
    "title": "我在无限游戏里封神 第二季（上）",
    "posterPath": "https://lain.bgm.tv/r/400/pic/cover/l/d8/be/479829_S513s.jpg",
    "releaseDate": "2024-01-01",
    "mediaType": "real",
    "rating": "",
    "description": "11话 /  2024-01-03 / 顺子、倒霉死勒",
    "link": "https://bgm.tv/subject/479829"
  },
  {
    "id": "479831",
    "type": "link",
    "title": "国师难为",
    "posterPath": "https://lain.bgm.tv/r/400/pic/cover/l/14/9e/479831_D23Ee.jpg",
    "releaseDate": "2024-01-01",
    "mediaType": "real",
    "rating": "",
    "description": "3话 /  2024-01-07 / 紫枫儿、小随",
    "link": "https://bgm.tv/subject/479831"
  },
  {
    "id": "479832",
    "type": "link",
    "title": "亲密距离",
    "posterPath": "https://lain.bgm.tv/r/400/pic/cover/l/8c/fc/479832_T9dSt.jpg",
    "releaseDate": "2024-01-01",
    "mediaType": "real",
    "rating": "",
    "description": "11话 /  2024-01-12 / 罗师傅、陈张太康",
    "link": "https://bgm.tv/subject/479832"
  },
  {
    "id": "479833",
    "type": "link",
    "title": "他是我先看上的",
    "posterPath": "https://lain.bgm.tv/r/400/pic/cover/l/66/0d/479833_C7pKq.jpg",
    "releaseDate": "2024-01-01",
    "mediaType": "real",
    "rating": "",
    "description": "16话 /  2024-01-17 / 路扬君、李白",
    "link": "https://bgm.tv/subject/479833"
  },
  {
    "id": "479835",
    "type": "link",
    "title": "教主与疯子",
    "posterPath": "https://lain.bgm.tv/r/400/pic/cover/l/8a/61/479835_N33QA.jpg",
    "releaseDate": "2024-01-01",
    "mediaType": "real",
    "rating": "",
    "description": "8话 /  2024-01-05 / 倔强的小红、杨昕燃",
    "link": "https://bgm.tv/subject/479835"
  },
  {
    "id": "479837",
    "type": "link",
    "title": "微醺公式",
    "posterPath": "https://lain.bgm.tv/r/400/pic/cover/l/cd/e7/479837_1b3rv.jpg",
    "releaseDate": "2024-01-01",
    "mediaType": "real",
    "rating": "",
    "description": "7话 /  2024-01-19 / 刘澄、张恩泽",
    "link": "https://bgm.tv/subject/479837"
  },
  {
    "id": "479853",
    "type": "link",
    "title": "万有引力 第二季",
    "posterPath": "https://lain.bgm.tv/r/400/pic/cover/l/8b/f3/479853_tqOAJ.jpg",
    "releaseDate": "2024-01-01",
    "mediaType": "real",
    "rating": "",
    "description": "16话 /  2024-02-29 / 陈张太康、胡良伟",
    "link": "https://bgm.tv/subject/479853"
  },
  {
    "id": "479912",
    "type": "link",
    "title": "竭泽而渔",
    "posterPath": "https://lain.bgm.tv/r/400/pic/cover/l/5e/df/479912_6u4qU.jpg",
    "releaseDate": "2024-01-01",
    "mediaType": "real",
    "rating": "",
    "description": "12话 /  2024-02-17 / 赖秋雨、陈张太康",
    "link": "https://bgm.tv/subject/479912"
  },
  {
    "id": "244813",
    "type": "tmdb",
    "title": "甜甜的陷阱",
    "posterPath": "https://image.tmdb.org/t/p/w500/wrVTfXyKC3suSiwzH9vqH4cz45S.jpg",
    "releaseDate": "2024-01-29",
    "mediaType": "tv",
    "rating": "7.1",
    "description": "学徒李柰（张淼怡 饰）为帮助师傅夺回代表荣誉的五星菜刀，“卧底敌营”，只为有朝一日打败“名厨杀手”姜芥（谢彬彬 饰），却跌入姜芥设计的“陷阱”。该剧以中华传统美食为背景，厨艺界小白与厨艺界“夺刀杀手”开启了一场斗智斗勇，相生相克的“甜斗”之路。",
    "link": null,
    "tmdb_id": "244813",
    "tmdb_site_id": "tv/244813",
    "tmdb_season_number": null,
    "tmdb_origin_countries": [
      "CN"
    ],
    "tmdb_source": "tmdb_api"
  },
  {
    "id": "235614",
    "type": "tmdb",
    "title": "生活在别处的我",
    "posterPath": "https://image.tmdb.org/t/p/w500/iNzhhRrrOXK4xCS8gTcdD90aGL4.jpg",
    "releaseDate": "2024-05-06",
    "mediaType": "tv",
    "rating": "6.7",
    "description": "夏果（钟楚曦 饰）生活在乐山，日子平静，与男友郁见（刘学义 饰）的感情平淡却甜蜜。她一直渴望生活能有一点不平凡。当她获得去上海的工作机会、两人正憧憬未来时，郁见的父亲突然病倒。夏果陷入两难：去，还是不去？\n\nA方案：\n\n夏果选择前往上海。在新环境中充满斗志，期待郁见早日与她相聚。然而友情考验、事业冲击与异地恋的痛苦接踵而至，她不时自问：如果当初留在乐山，人生是否会不同？\n\nB方案：\n\n夏果决定留在乐山，与郁见结婚生子，承担起照顾家庭的责任。然而体弱的公公、挑剔的婆婆和麻烦的小姑子让她疲惫不堪，加上郁见事业危机，两人感情也逐渐出现裂痕。\n\n上海的夏果最终与郁见分手，成熟稳重的总经理薛宇明（林雨申 饰）与阳光年轻的艾伦（姚弛 饰）先后走入她的生活，世界变得丰富却填补不了内心的孤独。乐山的夏果则被困于日常琐碎，为家庭、孩子与生计奔波，与郁见渐行渐远，人生陷入困局。\n\n当两种人生的夏果相遇，她们彼此询问：如果提前知晓结局，再重新选择，我们的人生是否会不一样？",
    "link": null,
    "tmdb_id": "235614",
    "tmdb_site_id": "tv/235614",
    "tmdb_season_number": null,
    "tmdb_origin_countries": [
      "CN"
    ],
    "tmdb_source": "tmdb_api"
  },
  {
    "id": "480018",
    "type": "link",
    "title": "すっぴんヒーロー",
    "posterPath": "https://lain.bgm.tv/r/400/pic/cover/l/1b/b2/480018_jbqq6.jpg",
    "releaseDate": "2024-02-24",
    "mediaType": "real",
    "rating": "",
    "description": "1话 /  2024年2月24日 / 丸山礼",
    "link": "https://bgm.tv/subject/480018"
  },
  {
    "id": "480066",
    "type": "link",
    "title": "純喫茶イニョン",
    "posterPath": "https://lain.bgm.tv/r/400/pic/cover/l/2e/a1/480066_eDM5o.jpg",
    "releaseDate": "2024-03-30",
    "mediaType": "real",
    "rating": "",
    "description": "4话 /  2024年3月30日 / チャンソン（2PM）",
    "link": "https://bgm.tv/subject/480066"
  },
  {
    "id": "480082",
    "type": "link",
    "title": "恋し続けて警護240日",
    "posterPath": "https://lain.bgm.tv/r/400/pic/cover/l/56/cd/480082_K6Msz.jpg",
    "releaseDate": "2024-02-10",
    "mediaType": "real",
    "rating": "",
    "description": "2024年2月10日 / 藤原丈一郎（なにわ男子）",
    "link": "https://bgm.tv/subject/480082"
  },
  {
    "id": "261134",
    "type": "tmdb",
    "title": "永夜长明",
    "posterPath": "https://image.tmdb.org/t/p/w500/geKJWRJi9pfyKoltPJWXqQte07B.jpg",
    "releaseDate": "2024-01-01",
    "mediaType": "tv",
    "rating": "7.3",
    "description": "谢家贵女谢挽音与太子李迟成婚当日，却意外目睹一场残忍的狩猎：传闻中清雅绝尘的国师东方醉，云淡风轻，含笑射杀了当朝国丈。谢挽音也因此成为了国师的猎物。果真，在东方醉的阴谋拨弄下，谢挽音与太子的婚礼发生惊变，但令谢挽音意外的是，东方醉并非想要杀了自己灭口——而是以谢家满门相要挟，逼迫谢挽音成为国师夫人。世人皆传，国师一袭白衣光风霁月，只有谢挽音知道，他是个残暴狠辣，穷凶极恶的疯子。宁死不屈、本性果敢的谢挽音毅然决定，杀掉这个疯子。新婚之夜，谢挽音筹谋已久，决心动手。却不料，东方醉笑盈盈地望向手持匕首的谢挽音，竟紧握她的手，带着她顺势将刀尖捅向自己的心口。“夫人想杀我，和我说一声便是，不必这么周折。”从此，谢挽音开始了与自己的国师夫君斗智斗勇，可渐渐的，她发现，东方醉似与她幼年一位故人颇为相像，而一场涉及两代人的经年阴谋，也开始在两人背后，渐渐露出了它的獠牙。",
    "link": null,
    "tmdb_id": "261134",
    "tmdb_site_id": "tv/261134",
    "tmdb_season_number": null,
    "tmdb_origin_countries": [
      "CN"
    ],
    "tmdb_source": "tmdb_api"
  },
  {
    "id": "273632",
    "type": "tmdb",
    "title": "入夜对她上瘾",
    "posterPath": "https://image.tmdb.org/t/p/w500/ynMnlaWNbf0NdAxFANMxewRYCf3.jpg",
    "releaseDate": "2024-01-01",
    "mediaType": "tv",
    "rating": "8.0",
    "description": "家境盘穷的林棉走投无路，险些误入歧途，幸得好心医生时凛救赎。时凛被她柔弱与坚强所吸引，为她抵御黑暗，筑起爱的堡垒。在时凛的守护下，林蜕变",
    "link": null,
    "tmdb_id": "273632",
    "tmdb_site_id": "tv/273632",
    "tmdb_season_number": null,
    "tmdb_origin_countries": [
      "CN"
    ],
    "tmdb_source": "tmdb_api"
  },
  {
    "id": "480263",
    "type": "link",
    "title": "向导是不是重生的 第二季",
    "posterPath": "https://lain.bgm.tv/r/400/pic/cover/l/f4/9d/480263_C3AaD.jpg",
    "releaseDate": "2024-01-01",
    "mediaType": "real",
    "rating": "",
    "description": "8话 /  2024-02-14 / 陈冠豪、张东",
    "link": "https://bgm.tv/subject/480263"
  },
  {
    "id": "480271",
    "type": "link",
    "title": "长风几万里 第一季",
    "posterPath": "https://lain.bgm.tv/r/400/pic/cover/l/0f/4d/480271_Xn332.jpg",
    "releaseDate": "2024-01-01",
    "mediaType": "real",
    "rating": "",
    "description": "12话 /  2024-02-24 / 谷江山、刘明月",
    "link": "https://bgm.tv/subject/480271"
  },
  {
    "id": "480394",
    "type": "link",
    "title": "Tracker Season 1",
    "posterPath": "https://lain.bgm.tv/r/400/pic/cover/l/5f/c5/480394_wxr05.jpg",
    "releaseDate": "2024-01-01",
    "mediaType": "real",
    "rating": "",
    "description": "13话 /  2024-02-11 / Hilary Weisman Graham / Ben Winters / Justin Hartley / Robin Weigert / Abby McEnany / Eric Graise / Fiona Rene",
    "link": "https://bgm.tv/subject/480394"
  },
  {
    "id": "480510",
    "type": "link",
    "title": "訳アリ女ダイアリー",
    "posterPath": "https://lain.bgm.tv/r/400/pic/cover/l/0c/a7/480510_95945.jpg",
    "releaseDate": "2024-03-02",
    "mediaType": "real",
    "rating": "",
    "description": "2024年3月2日 / 森川葵",
    "link": "https://bgm.tv/subject/480510"
  }
]
