[
  {
    "id": "157571",
    "type": "tmdb",
    "title": "勇者赫鲁库",
    "posterPath": "https://lain.bgm.tv/r/400/pic/cover/l/04/bb/369784_pdDS6.jpg",
    "releaseDate": "2023-07-11",
    "mediaType": "tv",
    "rating": "6.1",
    "description": "24话 /  2023年7月11日 / 佐藤竜雄 / 七尾ナナキ（小学館「マンガワン」連載） / 出野喜則；副人设：林奈美、長坂寛治",
    "link": null,
    "tmdb_id": "157571",
    "tmdb_site_id": "tv/157571",
    "tmdb_season_number": null,
    "tmdb_origin_countries": [],
    "tmdb_source": "bangumi_data"
  },
  {
    "id": "425173",
    "type": "link",
    "title": "冬天的馈赠",
    "posterPath": "https://lain.bgm.tv/r/400/pic/cover/l/11/71/425173_wkaAx.jpg",
    "releaseDate": "2023-03-18",
    "mediaType": "anime",
    "rating": "5.6",
    "description": "1话 /  2023年3月18日 / 寺澤和晃 / 川妻智美",
    "link": "https://bgm.tv/subject/425173"
  },
  {
    "id": "209604",
    "type": "tmdb",
    "title": "迪阿姆帝国物语～从断头台开始的，公主转生逆转传～",
    "posterPath": "https://lain.bgm.tv/r/400/pic/cover/l/6a/7c/400114_qXsEN.jpg",
    "releaseDate": "2023-10-07",
    "mediaType": "tv",
    "rating": "6.1",
    "description": "12话 /  2023年10月7日 / 伊部勇志 / 餅月望（TOブックス刊） / 大塚舞",
    "link": null,
    "tmdb_id": "209604",
    "tmdb_site_id": "tv/209604",
    "tmdb_season_number": null,
    "tmdb_origin_countries": [],
    "tmdb_source": "bangumi_data"
  },
  {
    "id": "1030587",
    "type": "tmdb",
    "title": "哆啦A梦：大雄与天空的理想乡",
    "posterPath": "https://lain.bgm.tv/r/400/pic/cover/l/41/68/390873_pKrd2.jpg",
    "releaseDate": "2023-03-03",
    "mediaType": "movie",
    "rating": "6.0",
    "description": "1话 /  2023年3月3日 / 堂山卓見 / 藤子・F・不二雄 / 小林麻衣子",
    "link": null,
    "tmdb_id": "1030587",
    "tmdb_site_id": "movie/1030587",
    "tmdb_season_number": null,
    "tmdb_origin_countries": [],
    "tmdb_source": "bangumi_data"
  },
  {
    "id": "445678",
    "type": "link",
    "title": "火之鸟 伊甸之花",
    "posterPath": "https://lain.bgm.tv/r/400/pic/cover/l/f2/6a/445678_AsZdi.jpg",
    "releaseDate": "2023-11-03",
    "mediaType": "anime",
    "rating": "5.9",
    "description": "1话 /  2023年11月3日 / 西見祥示郎 / 手塚治虫「火の鳥」（望郷編） / 西田達三",
    "link": "https://bgm.tv/subject/445678"
  },
  {
    "id": "210899",
    "type": "tmdb",
    "title": "众星齐聚",
    "posterPath": "https://lain.bgm.tv/r/400/pic/cover/l/03/6b/402659_r50j7.jpg",
    "releaseDate": "2023-01-07",
    "mediaType": "tv",
    "rating": "5.8",
    "description": "12话 /  2023年1月7日 / 牛嶋新一郎 / Project UniteUp! / まじろ；副人物设定：瀬川健寿",
    "link": null,
    "tmdb_id": "210899",
    "tmdb_site_id": "tv/210899",
    "tmdb_season_number": null,
    "tmdb_origin_countries": [],
    "tmdb_source": "bangumi_data"
  },
  {
    "id": "234740",
    "type": "tmdb",
    "title": "新上司是天然呆",
    "posterPath": "https://lain.bgm.tv/r/400/pic/cover/l/ed/79/435926_X95cc.jpg",
    "releaseDate": "2023-10-07",
    "mediaType": "tv",
    "rating": "5.8",
    "description": "12话 /  2023年10月7日 / 阿部記之 / いちかわ暖「新しい上司はど天然」（秋田書店「マンガクロス」連載） / 安田京弘",
    "link": null,
    "tmdb_id": "234740",
    "tmdb_site_id": "tv/234740",
    "tmdb_season_number": null,
    "tmdb_origin_countries": [],
    "tmdb_source": "bangumi_data"
  },
  {
    "id": "65931",
    "type": "tmdb",
    "title": "文豪野犬 第五季",
    "posterPath": "https://lain.bgm.tv/r/400/pic/cover/l/10/b4/426815_WHFN2.jpg",
    "releaseDate": "2023-07-12",
    "mediaType": "tv",
    "rating": "6.0",
    "description": "11话 /  2023年7月12日 / 五十嵐卓哉 / 朝霧カフカ；漫画：春河35（「ヤングエース」連載） / 新井伸浩",
    "link": null,
    "tmdb_id": "65931",
    "tmdb_site_id": "tv/65931",
    "tmdb_season_number": null,
    "tmdb_origin_countries": [],
    "tmdb_source": "bangumi_data"
  },
  {
    "id": "197368",
    "type": "tmdb",
    "title": "蓝色管弦乐",
    "posterPath": "https://lain.bgm.tv/r/400/pic/cover/l/fe/5d/377769_e4pyy.jpg",
    "releaseDate": "2023-04-09",
    "mediaType": "tv",
    "rating": "6.0",
    "description": "24话 /  2023年4月9日 / 岸誠二 / 阿久井真(小学館「マンガワン」連載中) / 森田和明",
    "link": null,
    "tmdb_id": "197368",
    "tmdb_site_id": "tv/197368",
    "tmdb_season_number": null,
    "tmdb_origin_countries": [],
    "tmdb_source": "bangumi_data"
  },
  {
    "id": "231502",
    "type": "tmdb",
    "title": "碧蓝航线 女王号令",
    "posterPath": "https://lain.bgm.tv/r/400/pic/cover/l/88/51/349222_zSfO3.jpg",
    "releaseDate": "2023-07-27",
    "mediaType": "tv",
    "rating": "5.9",
    "description": "2话 /  2023年7月27日 / 「アズールレーン」運営、槌居/一迅社 / 柳沢まさひで、平田雄三、新村香奈",
    "link": null,
    "tmdb_id": "231502",
    "tmdb_site_id": "tv/231502",
    "tmdb_season_number": null,
    "tmdb_origin_countries": [],
    "tmdb_source": "bangumi_data"
  },
  {
    "id": "209829",
    "type": "tmdb",
    "title": "凹凸魔女的母女故事",
    "posterPath": "https://lain.bgm.tv/r/400/pic/cover/l/bc/4b/400551_O4R7O.jpg",
    "releaseDate": "2023-10-01",
    "mediaType": "tv",
    "rating": "6.0",
    "description": "12话 /  2023年10月1日 / たかたまさひろ / ピロヤ（「COMICメテオ」連載） / 吉田美和",
    "link": null,
    "tmdb_id": "209829",
    "tmdb_site_id": "tv/209829",
    "tmdb_season_number": null,
    "tmdb_origin_countries": [],
    "tmdb_source": "bangumi_data"
  },
  {
    "id": "405213",
    "type": "link",
    "title": "永生 第二季",
    "posterPath": "https://lain.bgm.tv/r/400/pic/cover/l/05/b2/405213_CoX2Z.jpg",
    "releaseDate": "2023-07-08",
    "mediaType": "anime",
    "rating": "5.6",
    "description": "12话 /  2023年7月8日",
    "link": "https://bgm.tv/subject/405213"
  },
  {
    "id": "349223",
    "type": "link",
    "title": "剧场版 转生成为了只有乙女游戏破灭Flag的邪恶大小姐",
    "posterPath": "https://lain.bgm.tv/r/400/pic/cover/l/f1/78/349223_9E9j0.jpg",
    "releaseDate": "2023-12-08",
    "mediaType": "anime",
    "rating": "6.0",
    "description": "1话 /  2023年12月8日 / 井上圭介 / 山口悟（一迅社文庫アイリス／一迅社刊） / 大島美和",
    "link": "https://bgm.tv/subject/349223"
  },
  {
    "id": "400129",
    "type": "link",
    "title": "熊出没·伴我“熊芯”",
    "posterPath": "https://lain.bgm.tv/r/400/pic/cover/l/d5/74/400129_DADUB.jpg",
    "releaseDate": "2023-01-22",
    "mediaType": "anime",
    "rating": "5.7",
    "description": "1话 /  2023年1月22日 / 林永长、邵和麒",
    "link": "https://bgm.tv/subject/400129"
  },
  {
    "id": "1223906",
    "type": "tmdb",
    "title": "口罩男生明明不想恋爱",
    "posterPath": "https://lain.bgm.tv/r/400/pic/cover/l/32/fd/425606_yxIHx.jpg",
    "releaseDate": "2023-10-20",
    "mediaType": "movie",
    "rating": "5.1",
    "description": "1话 /  2023年10月20日 / 武市直子 / 参号ミツル「マスク男子は恋したくないのに」（ビボピーコミックス/リブレ刊） / 金田炎",
    "link": null,
    "tmdb_id": "1223906",
    "tmdb_site_id": "movie/1223906",
    "tmdb_season_number": null,
    "tmdb_origin_countries": [],
    "tmdb_source": "bangumi_data"
  },
  {
    "id": "443867",
    "type": "link",
    "title": "斗破苍穹 年番2",
    "posterPath": "https://lain.bgm.tv/r/400/pic/cover/l/cc/69/443867_JUguG.jpg",
    "releaseDate": "2023-07-16",
    "mediaType": "anime",
    "rating": "5.8",
    "description": "53话 /  2023年7月16日 / 温玮翔、陈百俊 / 天蚕土豆",
    "link": "https://bgm.tv/subject/443867"
  },
  {
    "id": "345804",
    "type": "link",
    "title": "全职法师 第六季",
    "posterPath": "https://lain.bgm.tv/r/400/pic/cover/l/64/c6/345804_4E11y.jpg",
    "releaseDate": "2023-06-02",
    "mediaType": "anime",
    "rating": "5.4",
    "description": "12话 /  2023年6月2日 / 乱 / 管振宇",
    "link": "https://bgm.tv/subject/345804"
  },
  {
    "id": "214540",
    "type": "tmdb",
    "title": "亡骸游戏",
    "posterPath": "https://lain.bgm.tv/r/400/pic/cover/l/67/45/408013_5Z5Q3.jpg",
    "releaseDate": "2023-04-10",
    "mediaType": "tv",
    "rating": "6.0",
    "description": "12话 /  2023年4月10日 / 小野学 / 成田良悟・ 藤本新太（掲載「ヤングガンガン」スクウェア・エニックス刊） / 阿部恒",
    "link": null,
    "tmdb_id": "214540",
    "tmdb_site_id": "tv/214540",
    "tmdb_season_number": null,
    "tmdb_origin_countries": [],
    "tmdb_source": "bangumi_data"
  },
  {
    "id": "408858",
    "type": "link",
    "title": "魔女最后和那个客人一起。。。",
    "posterPath": "/img/no_icon_subject.png",
    "releaseDate": "2023-02-24",
    "mediaType": "anime",
    "rating": "5.8",
    "description": "2话 /  2023年2月24日 / 西義之（ナイーブタ）「魔女は結局その客と。。。」",
    "link": "https://bgm.tv/subject/408858"
  },
  {
    "id": "123525",
    "type": "tmdb",
    "title": "世界尽头的圣骑士 铁锈之山的君王",
    "posterPath": "https://lain.bgm.tv/r/400/pic/cover/l/83/6c/363569_dmZDf.jpg",
    "releaseDate": "2023-10-07",
    "mediaType": "tv",
    "rating": "5.9",
    "description": "12话 /  2023年10月7日 / 岩永彰 / 柳野かなた（オーバーラップ文庫刊） / 新井達也、羽田浩二",
    "link": null,
    "tmdb_id": "123525",
    "tmdb_site_id": "tv/123525/season/2",
    "tmdb_season_number": 2,
    "tmdb_origin_countries": [],
    "tmdb_source": "bangumi_data"
  },
  {
    "id": "137065",
    "type": "tmdb",
    "title": "明日方舟：冬隐归路",
    "posterPath": "https://lain.bgm.tv/r/400/pic/cover/l/e0/e3/411268_wIh3G.jpg",
    "releaseDate": "2023-10-06",
    "mediaType": "tv",
    "rating": "5.9",
    "description": "8话 /  2023年10月6日 / 渡邉祐記 / Hypergryph / Studio Montagne(鹰角网络) / 高藤彩",
    "link": null,
    "tmdb_id": "137065",
    "tmdb_site_id": "tv/137065/season/2",
    "tmdb_season_number": 2,
    "tmdb_origin_countries": [],
    "tmdb_source": "bangumi_data"
  },
  {
    "id": "210181",
    "type": "tmdb",
    "title": "奇异贤伴 黑色天使",
    "posterPath": "https://lain.bgm.tv/r/400/pic/cover/l/0f/dc/401301_WZVPG.jpg",
    "releaseDate": "2023-07-10",
    "mediaType": "tv",
    "rating": "5.9",
    "description": "12话 /  2023年7月10日 / 山本裕介 / MAGUS / 桂憲一郎",
    "link": null,
    "tmdb_id": "210181",
    "tmdb_site_id": "tv/210181",
    "tmdb_season_number": null,
    "tmdb_origin_countries": [],
    "tmdb_source": "bangumi_data"
  },
  {
    "id": "393719",
    "type": "link",
    "title": "妹妹是辣妹真是可爱",
    "posterPath": "/img/no_icon_subject.png",
    "releaseDate": "2023-02-03",
    "mediaType": "anime",
    "rating": "5.8",
    "description": "2话 /  2023年2月3日 / 「いもうとはGALかわいい」（著：わかつきひかる 絵：犬江しんすけ 出版：フランス書院）",
    "link": "https://bgm.tv/subject/393719"
  },
  {
    "id": "403696",
    "type": "link",
    "title": "少年歌行 海外仙山篇",
    "posterPath": "https://lain.bgm.tv/r/400/pic/cover/l/c0/aa/403696_6G6cM.jpg",
    "releaseDate": "2023-10-25",
    "mediaType": "anime",
    "rating": "5.4",
    "description": "26话 /  2023年10月25日 / 李萌 / 周木楠",
    "link": "https://bgm.tv/subject/403696"
  }
]
