[
  {
    "id": "496213",
    "type": "link",
    "title": "Mr. Jimmy",
    "posterPath": "https://lain.bgm.tv/r/400/pic/cover/l/dc/fc/496213_YIYRS.jpg",
    "releaseDate": "2023-01-01",
    "mediaType": "real",
    "rating": "",
    "description": "1话 /  2023-09-01 / Peter Michael Dowd / ジミー桜井",
    "link": "https://bgm.tv/subject/496213"
  },
  {
    "id": "230364",
    "type": "tmdb",
    "title": "杀人不难",
    "posterPath": "https://image.tmdb.org/t/p/w500/4Ced0ExBzhOsEsMBdghOm0OqurG.jpg",
    "releaseDate": "2023-01-01",
    "mediaType": "tv",
    "rating": "5.2",
    "description": "1954年的英格兰，在一列开往伦敦的火车上，卢克·菲茨威廉（戴维·荣松 David Jonsson 饰）遇到了平克顿小姐（佩内洛普·威尔顿 Penelope Wilton 饰），平克顿小姐说在英格兰平静的乡村威奇伍德发生了一起连环杀人案，并且推测说下一个被害者将是当地的医生。菲茨威廉不相信她的话，认为那只是她的胡思乱想。但是，数小时后，平克顿小姐死于一场车祸，车辆肇事后逃逸。仅仅是巧合吗？卢克倾向于认为如此——直到他几天后在《泰晤士报》上读到亨伯比医生意外死亡的讣告……卢克必须马上找出真凶，因为对某些人来说，杀人不难。",
    "link": null,
    "tmdb_id": "230364",
    "tmdb_site_id": "tv/230364",
    "tmdb_season_number": null,
    "tmdb_origin_countries": [
      "GB"
    ],
    "tmdb_source": "tmdb_api"
  },
  {
    "id": "492677",
    "type": "link",
    "title": "MyGO!!!!! 4th LIVE「前へ進む音の中で」",
    "posterPath": "https://lain.bgm.tv/r/400/pic/cover/l/3d/5d/492677_9xXVz.jpg",
    "releaseDate": "2023-01-01",
    "mediaType": "real",
    "rating": "7.1",
    "description": "1话 /  2023-04-09 / MyGO!!!!!",
    "link": "https://bgm.tv/subject/492677"
  },
  {
    "id": "492675",
    "type": "link",
    "title": "MyGO!!!!! 5th LIVE「迷うことに迷わない」",
    "posterPath": "https://lain.bgm.tv/r/400/pic/cover/l/d9/f3/492675_fB3wB.jpg",
    "releaseDate": "2023-01-01",
    "mediaType": "real",
    "rating": "7.3",
    "description": "1话 /  2023-08-12 / MyGO!!!!!",
    "link": "https://bgm.tv/subject/492675"
  },
  {
    "id": "485889",
    "type": "link",
    "title": "神探南茜 第四季",
    "posterPath": "https://lain.bgm.tv/r/400/pic/cover/l/4f/b3/485889_o2cC9.jpg",
    "releaseDate": "2023-01-01",
    "mediaType": "real",
    "rating": "",
    "description": "13话 /  2023-05-31",
    "link": "https://bgm.tv/subject/485889"
  },
  {
    "id": "429646",
    "type": "link",
    "title": "好想做一次 第四季",
    "posterPath": null,
    "releaseDate": "2023-06-08",
    "mediaType": "real",
    "rating": "",
    "description": "2023年6月8日 / Lang Fisher、Mindy Kaling / DeShawn Cavanaugh、Michael Cimino、Jeff Garlin",
    "link": "https://bgm.tv/subject/429646"
  },
  {
    "id": "548616",
    "type": "link",
    "title": "新生代舞台剧 德凯篇 Stage 5 通往远方的道路",
    "posterPath": "https://lain.bgm.tv/r/400/pic/cover/l/1b/d8/548616_cJiRF.jpg",
    "releaseDate": "2023-04-16",
    "mediaType": "real",
    "rating": "",
    "description": "2023年4月16日 / 松本大輝、寺坂頼我",
    "link": "https://bgm.tv/subject/548616"
  },
  {
    "id": "547348",
    "type": "link",
    "title": "新世代舞台剧 布莱泽奥特曼篇~循环的许愿星 SIDE布莱泽~/群星篇 ~循环的许愿星 SIDE群星~",
    "posterPath": "https://lain.bgm.tv/r/400/pic/cover/l/cc/af/547348_T53pe.jpg",
    "releaseDate": "2023-08-09",
    "mediaType": "real",
    "rating": "",
    "description": "2023年8月9日 / 坂口俊昭 / 蕨野友也",
    "link": "https://bgm.tv/subject/547348"
  },
  {
    "id": "550194",
    "type": "link",
    "title": "新生代舞台剧 群星篇 STAGE1 〜与未来连接的战士们〜",
    "posterPath": "https://lain.bgm.tv/r/400/pic/cover/l/00/be/550194_dLA8A.jpg",
    "releaseDate": "2023-04-07",
    "mediaType": "real",
    "rating": "",
    "description": "2话 /  2023年4月7日 / 金光大輔 / 根本史彦",
    "link": "https://bgm.tv/subject/550194"
  },
  {
    "id": "547423",
    "type": "link",
    "title": "新世代舞台剧 群星篇 ~新生代的战士们/布莱泽奥特曼篇 ~新的光芒~",
    "posterPath": "https://lain.bgm.tv/r/400/pic/cover/l/b9/76/547423_wz2X9.jpg",
    "releaseDate": "2023-07-22",
    "mediaType": "real",
    "rating": "",
    "description": "2023年7月22日 / 金光大輔 / 橋渡竜馬、菊地留以、武田彩里、蕨野友也（映像出演）",
    "link": "https://bgm.tv/subject/547423"
  },
  {
    "id": "203178",
    "type": "tmdb",
    "title": "老娘还没死",
    "posterPath": "https://image.tmdb.org/t/p/w500/yfnSAZtpl9A0hZVdjFIQhUneDJt.jpg",
    "releaseDate": "2023-01-01",
    "mediaType": "tv",
    "rating": "7.0",
    "description": "Nell本是一名成功的记者，为了帮助当时的未婚夫餐厅开业而搁置了事业- -如今重回文字事业的她，被迫接受了目前唯一能得到的工作，那就是写讣告。看起来这像是人生的又一层倒退，却或许帮助Nell理清了继续前进的想法。",
    "link": null,
    "tmdb_id": "203178",
    "tmdb_site_id": "tv/203178",
    "tmdb_season_number": null,
    "tmdb_origin_countries": [
      "US"
    ],
    "tmdb_source": "tmdb_api"
  },
  {
    "id": "223313",
    "type": "tmdb",
    "title": "禁忌痴恋",
    "posterPath": "https://image.tmdb.org/t/p/w500/16e4P50hXTGtylWKbEMFlvHYtMH.jpg",
    "releaseDate": "2023-01-01",
    "mediaType": "tv",
    "rating": "6.4",
    "description": "受人敬仰的伦敦外科医生与他儿子的未婚妻发生私情，这场爱欲横流的痴恋有可能彻底改变他们的人生。",
    "link": null,
    "tmdb_id": "223313",
    "tmdb_site_id": "tv/223313",
    "tmdb_season_number": null,
    "tmdb_origin_countries": [
      "GB"
    ],
    "tmdb_source": "tmdb_api"
  },
  {
    "id": "466579",
    "type": "link",
    "title": "ONE DAY Episode0",
    "posterPath": null,
    "releaseDate": "2023-11-20",
    "mediaType": "real",
    "rating": "",
    "description": "3话 /  2023年11月20日 / 二宮和也、中谷美紀、大沢たかお、中川大志、梶原善、桜井ユキ",
    "link": "https://bgm.tv/subject/466579"
  },
  {
    "id": "443011",
    "type": "link",
    "title": "ONE DAY～平安夜的骚动～",
    "posterPath": "https://lain.bgm.tv/r/400/pic/cover/l/66/1b/443011_hefxd.jpg",
    "releaseDate": "2023-01-01",
    "mediaType": "real",
    "rating": "5.7",
    "description": "11话 /  2023-10-09 / 鈴木雅之、三橋利行、柳沢凌介 / 徳永友一 / 二宮和也、中谷美紀、大沢たかお",
    "link": "https://bgm.tv/subject/443011"
  },
  {
    "id": "37854",
    "type": "tmdb",
    "title": "航海王",
    "posterPath": "https://lain.bgm.tv/r/400/pic/cover/l/2f/26/219775_N5l3H.jpg",
    "releaseDate": "2023-01-01",
    "mediaType": "tv",
    "rating": "6.8",
    "description": "8话 /  2023-08-31 / Matt Owens、Steven Maeda、Ian Stokes、Allison Weintraub、Laura Jacqmin、Jason Cho、Damani Johnson、Lindsay Gelfand、尾田栄一郎 (创意监修) / Iñaki Godoy / Emily Rudd / Mackenyu(新田真剣佑) / Jacob Romero Gibson / Taz Skylar / Vincent Regan / Jeff Ward / Morgan Davies",
    "link": null,
    "tmdb_id": "37854",
    "tmdb_site_id": "tv/37854",
    "tmdb_season_number": null,
    "tmdb_origin_countries": [],
    "tmdb_source": "bangumi_data"
  },
  {
    "id": "630426",
    "type": "link",
    "title": "ONE PIECE ON ICE ～エピソード・オブ・アラバスタ～",
    "posterPath": "https://lain.bgm.tv/r/400/pic/cover/l/23/aa/630426_A2ARj.jpg",
    "releaseDate": "2023-01-01",
    "mediaType": "real",
    "rating": "",
    "description": "2023-08-11 / 金谷かほり / 宇野昌磨、島田高志郎、友野一希、織田信成、渡辺倫果、本田真凜、本田望結、無良崇人、田中刑事、本郷理華、小川真理恵、プリンスアイスワールド",
    "link": "https://bgm.tv/subject/630426"
  },
  {
    "id": "447230",
    "type": "link",
    "title": "公寓大楼里的谋杀案 第三季",
    "posterPath": "https://lain.bgm.tv/r/400/pic/cover/l/e8/d1/447230_6MqMY.jpg",
    "releaseDate": "2023-01-01",
    "mediaType": "real",
    "rating": "7.2",
    "description": "10话 /  2023-08-07 / John Hoffman / Steve Martin、John Hoffman、Sas Goldberg / Steve Martin、Martin Short、Selena Gomez",
    "link": "https://bgm.tv/subject/447230"
  },
  {
    "id": "448634",
    "type": "link",
    "title": "海盗旗升起 第二季",
    "posterPath": "https://lain.bgm.tv/r/400/pic/cover/l/0b/f8/448634_8nbD9.jpg",
    "releaseDate": "2023-01-01",
    "mediaType": "real",
    "rating": "",
    "description": "8话 /  2023-10-05",
    "link": "https://bgm.tv/subject/448634"
  },
  {
    "id": "441025",
    "type": "link",
    "title": "我们的星球 第二季",
    "posterPath": "https://lain.bgm.tv/r/400/pic/cover/l/37/e1/441025_JTCjv.jpg",
    "releaseDate": "2023-01-01",
    "mediaType": "real",
    "rating": "",
    "description": "4话 /  2023-06-14",
    "link": "https://bgm.tv/subject/441025"
  },
  {
    "id": "196421",
    "type": "tmdb",
    "title": "Os Outros",
    "posterPath": "https://image.tmdb.org/t/p/w500/qXeqUSGQi7Ld91t1xpJGy12laY7.jpg",
    "releaseDate": "2023-01-01",
    "mediaType": "tv",
    "rating": "7.4",
    "description": "2023-11-17 / 品川ヒロシ / 品川ヒロシ / 倉悠貴",
    "link": null,
    "tmdb_id": "196421",
    "tmdb_site_id": "tv/196421",
    "tmdb_season_number": null,
    "tmdb_origin_countries": [
      "BR"
    ],
    "tmdb_source": "tmdb_api"
  },
  {
    "id": "441646",
    "type": "link",
    "title": "古战场传奇 第七季",
    "posterPath": "https://lain.bgm.tv/r/400/pic/cover/l/ed/71/441646_jJ62j.jpg",
    "releaseDate": "2023-01-01",
    "mediaType": "real",
    "rating": "",
    "description": "16话 /  2023-06-16",
    "link": "https://bgm.tv/subject/441646"
  },
  {
    "id": "233374",
    "type": "tmdb",
    "title": "故事新编",
    "posterPath": "https://image.tmdb.org/t/p/w500/pe20BNk0suzIO7icVfHgyJB2hih.jpg",
    "releaseDate": "2023-01-01",
    "mediaType": "tv",
    "rating": "0.0",
    "description": "6话 /  2023-11-12 / 城定秀夫、吉田康弘、松本優作、前田弘二、工藤梨穂、近藤啓介 / 城定秀夫、吉田康弘、高田亮、狗飼恭子、近藤啓介 / 田中圭、柄本佑、前田敦子、成田凌、石橋静河、中川大志",
    "link": null,
    "tmdb_id": "233374",
    "tmdb_site_id": "tv/233374",
    "tmdb_season_number": null,
    "tmdb_origin_countries": [
      "JP"
    ],
    "tmdb_source": "tmdb_api"
  },
  {
    "id": "158083",
    "type": "tmdb",
    "title": "无痛杀手",
    "posterPath": "https://image.tmdb.org/t/p/w500/7zYtVymTxVEhgAOuMl4l2NoFCrO.jpg",
    "releaseDate": "2023-01-01",
    "mediaType": "tv",
    "rating": "7.2",
    "description": "《无痛杀手》是一部有脚本的限定剧集，故事情节虚构，探讨了美国阿片类药物危机的起源和后果，重点讲述了肇事者、受害者和寻求真相者的故事，他们的生活因奥施康定的发明彻底改变了。《无痛杀手》对犯罪、问责制和屡屡令数十万美国人失败的制度进行了审视，改编自巴里·迈耶的《PAINKILLER》一书和帕特里克·拉登·基夫在《纽约客》杂志上发表的文章《The Family That Built an Empire of Pain》。监制阵容包括埃里克·纽曼、彼得·博格和亚历克斯·吉布尼，以及剧集主管/创剧人迈卡·费兹曼-布卢和诺亚·哈普斯特。主演阵容包括乌佐·阿杜巴、马修·布罗德里克、泰勒·克奇、迪纳·什瓦比和韦斯特·杜乔夫尼。",
    "link": null,
    "tmdb_id": "158083",
    "tmdb_site_id": "tv/158083",
    "tmdb_season_number": null,
    "tmdb_origin_countries": [
      "US"
    ],
    "tmdb_source": "tmdb_api"
  },
  {
    "id": "461529",
    "type": "link",
    "title": "波西·杰克逊与奥林匹亚众神",
    "posterPath": "https://lain.bgm.tv/r/400/pic/cover/l/7c/6a/461529_5xeac.jpg",
    "releaseDate": "2023-12-20",
    "mediaType": "real",
    "rating": "",
    "description": "8话 /  2023年12月20日 / Rick Riordan, Jon Steinberg",
    "link": "https://bgm.tv/subject/461529"
  }
]
