[
  {
    "id": "211748",
    "type": "tmdb",
    "title": "有院子的家",
    "posterPath": "https://image.tmdb.org/t/p/w500/or8j3ZGC4bzcCdoYXSzDs4VOGM4.jpg",
    "releaseDate": "2023-01-01",
    "mediaType": "tv",
    "rating": "7.5",
    "description": "讲述金泰希饰演的文珠兰在拥有医生丈夫、聪明帅气的儿子的富足家庭里，享受着让人艳羡的完美幸福生活的家庭主妇，自从在后院闻到可疑的味道后，她的日常生活开始出现裂痕，与林智妍饰演的家暴受害者秋尚恩偶然相遇后，更是让自己陷入混乱之中。",
    "link": null,
    "tmdb_id": "211748",
    "tmdb_site_id": "tv/211748",
    "tmdb_season_number": null,
    "tmdb_origin_countries": [
      "KR"
    ],
    "tmdb_source": "tmdb_api"
  },
  {
    "id": "156888",
    "type": "tmdb",
    "title": "假面女郎",
    "posterPath": "https://image.tmdb.org/t/p/w500/3mNlEF4HB7e9WJjNXj43XPWteJu.jpg",
    "releaseDate": "2023-01-01",
    "mediaType": "tv",
    "rating": "7.4",
    "description": "一个对自己外表不自信的办公室职员在夜晚变身为假面网红，但一连串不幸事件却颠覆了她的生活。",
    "link": null,
    "tmdb_id": "156888",
    "tmdb_site_id": "tv/156888",
    "tmdb_season_number": null,
    "tmdb_origin_countries": [
      "KR"
    ],
    "tmdb_source": "tmdb_api"
  },
  {
    "id": "211051",
    "type": "tmdb",
    "title": "我的恶魔",
    "posterPath": "https://lain.bgm.tv/r/400/pic/cover/l/c3/5f/461840_abtFh.jpg",
    "releaseDate": "2023-01-01",
    "mediaType": "tv",
    "rating": "",
    "description": "16话 /  2023-11-24 / 김장한、권다솜 / 최아일 / 김유정(金裕贞)、송강(宋江)、이상이(李相二)",
    "link": null,
    "tmdb_id": "211051",
    "tmdb_site_id": "tv/211051",
    "tmdb_season_number": null,
    "tmdb_origin_countries": [],
    "tmdb_source": "bangumi_data"
  },
  {
    "id": "428842",
    "type": "link",
    "title": "模范出租车2",
    "posterPath": "https://lain.bgm.tv/r/400/pic/cover/l/b8/01/428842_ahd8F.jpg",
    "releaseDate": "2023-01-01",
    "mediaType": "real",
    "rating": "6.8",
    "description": "16话 /  2023-02-17 / 이단(李丹)、장영석 / 오상호(吴相浩) / 이제훈(李帝勋)、김의성( 金义城)、표예진(表艺珍)、장혁진(张赫镇)、배유람(裴侑蓝)、신재하(辛载夏)",
    "link": "https://bgm.tv/subject/428842"
  },
  {
    "id": "126485",
    "type": "tmdb",
    "title": "超异能族",
    "posterPath": "https://image.tmdb.org/t/p/w500/4iaJvLUc6cIpUQn56llNV2p9lcP.jpg",
    "releaseDate": "2023-01-01",
    "mediaType": "tv",
    "rating": "0.0",
    "description": "本剧是一部超能力英雄动作剧集，讲述藏起超能力生活于现在的孩子们和隐藏过去痛苦秘密生活着的父母们，一同面对跨越时代与世代席卷而来的巨大危机。",
    "link": null,
    "tmdb_id": "126485",
    "tmdb_site_id": "tv/126485",
    "tmdb_season_number": null,
    "tmdb_origin_countries": [
      "KR"
    ],
    "tmdb_source": "tmdb_api"
  },
  {
    "id": "216310",
    "type": "tmdb",
    "title": "无人岛的DIVA",
    "posterPath": "https://image.tmdb.org/t/p/w500/cWFKB5E5tuEc7ZwIl0hT6BCLiAd.jpg",
    "releaseDate": "2023-01-01",
    "mediaType": "tv",
    "rating": "8.0",
    "description": "立志成为歌手的她被困在一个偏远岛屿十五年。回归社会后，她不惜一切代价追逐自己的天后梦想。",
    "link": null,
    "tmdb_id": "216310",
    "tmdb_site_id": "tv/216310",
    "tmdb_season_number": null,
    "tmdb_origin_countries": [
      "KR"
    ],
    "tmdb_source": "tmdb_api"
  },
  {
    "id": "204654",
    "type": "tmdb",
    "title": "诱饵",
    "posterPath": "https://image.tmdb.org/t/p/w500/Ak8S6qZKvNFKLxVsrtzAC60HAQV.jpg",
    "releaseDate": "2023-01-27",
    "mediaType": "tv",
    "rating": "8.1",
    "description": "通过令人发指的时事揭露过去未解决案件的真相的故事。",
    "link": null,
    "tmdb_id": "204654",
    "tmdb_site_id": "tv/204654",
    "tmdb_season_number": null,
    "tmdb_origin_countries": [
      "KR"
    ],
    "tmdb_source": "tmdb_api"
  },
  {
    "id": "210272",
    "type": "tmdb",
    "title": "朴夏京旅行记",
    "posterPath": "https://image.tmdb.org/t/p/w500/fumf21EdFlDqqUFsGEVXNF03ng9.jpg",
    "releaseDate": "2023-01-01",
    "mediaType": "tv",
    "rating": "7.9",
    "description": "该剧讲述语文老师朴夏京在周六一个人独自旅行遇见形形色色的人的治愈旅行记故事。",
    "link": null,
    "tmdb_id": "210272",
    "tmdb_site_id": "tv/210272",
    "tmdb_season_number": null,
    "tmdb_origin_countries": [
      "KR"
    ],
    "tmdb_source": "tmdb_api"
  },
  {
    "id": "212204",
    "type": "tmdb",
    "title": "闪亮的西瓜",
    "posterPath": "https://image.tmdb.org/t/p/w500/iXnYxGWRJhr9axVwJ2ohlxX6Jzb.jpg",
    "releaseDate": "2023-01-01",
    "mediaType": "tv",
    "rating": "8.8",
    "description": "讲述模范生CODA少年，透过一间可疑的乐器行穿越过去后，与当时同龄的父亲成为好友，一起组建了乐队，还和神秘的少女展开初恋的青春成长故事。（CODA是“Child of Deaf Adults”的缩写，意为“听觉障碍者的小孩”）",
    "link": null,
    "tmdb_id": "212204",
    "tmdb_site_id": "tv/212204",
    "tmdb_season_number": null,
    "tmdb_origin_countries": [
      "KR"
    ],
    "tmdb_source": "tmdb_api"
  },
  {
    "id": "229915",
    "type": "tmdb",
    "title": "夜幕降临",
    "posterPath": "https://image.tmdb.org/t/p/w500/gWdkUI4AJdshzbCrKEegBBJGY08.jpg",
    "releaseDate": "2023-01-01",
    "mediaType": "tv",
    "rating": "7.8",
    "description": "剧情讲述唯一高中二年三班的学生们修学旅行期间，在受到诅咒的训练所里，突然被迫参加一场不可能逃脱的致命游戏，展开激烈的欺骗心理战并为生存而奋斗的故事。",
    "link": null,
    "tmdb_id": "229915",
    "tmdb_site_id": "tv/229915",
    "tmdb_season_number": null,
    "tmdb_origin_countries": [
      "KR"
    ],
    "tmdb_source": "tmdb_api"
  },
  {
    "id": "158258",
    "type": "tmdb",
    "title": "课后战争活动",
    "posterPath": "https://image.tmdb.org/t/p/w500/pKedAAy9KuWFPVDJCR2kcVb9ApL.jpg",
    "releaseDate": "2023-01-01",
    "mediaType": "tv",
    "rating": "8.2",
    "description": "某一天世上突然出现了未知的宝蓝色球状生命体，给人类带来了伤害，中大型的球体可以伤人，小型球体会攻击人，在危机事态下，全国的高中生都接受军事训练，被编制成军人预备军，开始在全国各个地区拿枪战斗，预备军人的任务是防御和摧毁部署在前线向市中心移动的小型球体。 主要是一部讲述高中生变成军人开始拿枪战斗的故事",
    "link": null,
    "tmdb_id": "158258",
    "tmdb_site_id": "tv/158258",
    "tmdb_season_number": null,
    "tmdb_origin_countries": [
      "KR"
    ],
    "tmdb_source": "tmdb_api"
  },
  {
    "id": "627775",
    "type": "link",
    "title": "犯罪都市3",
    "posterPath": "https://lain.bgm.tv/r/400/pic/cover/l/29/ff/627775_5G0ZQ.jpg",
    "releaseDate": "2023-05-31",
    "mediaType": "real",
    "rating": "",
    "description": "2023年5月31日 / 이상용 / 김민성、차우진 / 마동석、이준혁、青木崇高",
    "link": "https://bgm.tv/subject/627775"
  },
  {
    "id": "236887",
    "type": "tmdb",
    "title": "偶像升级计划",
    "posterPath": "https://image.tmdb.org/t/p/w500/7GznVBciuRCmb8VhbrbKadsrCtR.jpg",
    "releaseDate": "2023-01-01",
    "mediaType": "tv",
    "rating": "6.0",
    "description": "偶像升级计划现代都市爱情韩剧，这个故事围绕着五年级练习生和即将出道的偶像Eden以及同一经纪公司的名人JiHoon展开，讲述了即将作为男团出道的伊登遇到了与他同属一家公司的过气名人智勋，伊登被告知只有与志勋一起进行「商业同性恋表演」(BGP)才能出道。伊甸园想要拒绝这样的现实，但他遵循经纪公司希望他作为出道的梦想做的事情。伊登在一个名为男子乐队中工作时，对“BGP”感到厌恶，智勋自然地接近并取笑他，两人继续争吵，与此同时，随着玄彬和杰伊的出现，伊登和智勋之间的误会越来越大……他们能否解开误会，找到彼此的真情呢?",
    "link": null,
    "tmdb_id": "236887",
    "tmdb_site_id": "tv/236887",
    "tmdb_season_number": null,
    "tmdb_origin_countries": [
      "KR"
    ],
    "tmdb_source": "tmdb_api"
  },
  {
    "id": "209751",
    "type": "tmdb",
    "title": "法钱",
    "posterPath": "https://image.tmdb.org/t/p/w500/1JUI0A3a1Q2HH8J0HotpXQNbxNv.jpg",
    "releaseDate": "2023-01-01",
    "mediaType": "tv",
    "rating": "6.2",
    "description": "富商殷勇是个已跻身资本家行列的金融巨鳄，近年来一直隐居于蒙古国的牧场。由于外甥泰春和已故恩人的女儿俊京的求助，他回到了韩国。为了保护挚爱的家人，并为一位故去的老友复仇，殷勇准备与腐败势力开战。然而，当操纵黑钱与玩弄权术的势力互相勾结，力量远比他想象的更为强大。敌人的反击虽然幼稚，却残忍致命。在这个阴谋与背叛横行的战场上，殷勇三人逐渐各自为阵，用自己的方式惩戒邪恶之人。他们能否打破这些绝对权力者的腐败勾结，让正义得以伸张？",
    "link": null,
    "tmdb_id": "209751",
    "tmdb_site_id": "tv/209751",
    "tmdb_season_number": null,
    "tmdb_origin_countries": [
      "KR"
    ],
    "tmdb_source": "tmdb_api"
  },
  {
    "id": "220951",
    "type": "tmdb",
    "title": "非故意恋爱故事",
    "posterPath": "https://image.tmdb.org/t/p/w500/uzfltKWnKpiqSis8ZZi1ArhpNLV.jpg",
    "releaseDate": "2023-01-01",
    "mediaType": "tv",
    "rating": "6.7",
    "description": "本剧改编自人气网络漫画，讲述了从谎言开始的一段关系发展为真爱的故事，车瑞元将饰演突然间失去踪迹的天才陶艺师，而则将饰演原本有着令人羡慕的工作，却突然面临失业危机，要保住饭碗就必须要找到天才陶艺师的某大企业职员。",
    "link": null,
    "tmdb_id": "220951",
    "tmdb_site_id": "tv/220951",
    "tmdb_season_number": null,
    "tmdb_origin_countries": [
      "KR"
    ],
    "tmdb_source": "tmdb_api"
  },
  {
    "id": "205082",
    "type": "tmdb",
    "title": "非法正义",
    "posterPath": "https://image.tmdb.org/t/p/w500/rC4aeRcoXw4MqTdyl5gEnsKRSiI.jpg",
    "releaseDate": "2023-01-01",
    "mediaType": "tv",
    "rating": "8.4",
    "description": "这部动作惊悚剧讲述在白天守护法律的警察大学模范生金智勇，到了晚上却成为「治安维持者」，亲自审判逃过法网的罪犯，以及各自怀着不同目的围绕在他身边的人的故事。",
    "link": null,
    "tmdb_id": "205082",
    "tmdb_site_id": "tv/205082",
    "tmdb_season_number": null,
    "tmdb_origin_countries": [
      "KR"
    ],
    "tmdb_source": "tmdb_api"
  },
  {
    "id": "127529",
    "type": "tmdb",
    "title": "猎犬",
    "posterPath": "https://image.tmdb.org/t/p/w500/f3EBwYRGPRv3peMdKjwbPaPB8m9.jpg",
    "releaseDate": "2023-01-01",
    "mediaType": "tv",
    "rating": "8.4",
    "description": "两名年轻的拳击手与心地善良的放贷人联手对抗趁人之危的冷酷高利贷者。",
    "link": null,
    "tmdb_id": "127529",
    "tmdb_site_id": "tv/127529",
    "tmdb_season_number": null,
    "tmdb_origin_countries": [
      "KR"
    ],
    "tmdb_source": "tmdb_api"
  },
  {
    "id": "215471",
    "type": "tmdb",
    "title": "这是爱情吗",
    "posterPath": "https://image.tmdb.org/t/p/w500/tmtKt7QLm7HbzS5aNNxtdvk2bZJ.jpg",
    "releaseDate": "2023-01-01",
    "mediaType": "tv",
    "rating": "8.2",
    "description": "和断绝关系13年父亲的讣闻一同传来晴天霹雳的消息是，必须从一家人住了一辈子的房子搬出去。一夕之间被扫地出门，委屈得睡不着觉的宇宙决心报仇，以牙还牙，以眼还眼。然而报仇的对象冬辰却是个连影子都看起来很孤单，甚至令人心疼的单纯男人。她真的能成功实行她的复仇计划吗？",
    "link": null,
    "tmdb_id": "215471",
    "tmdb_site_id": "tv/215471",
    "tmdb_season_number": null,
    "tmdb_origin_countries": [
      "KR"
    ],
    "tmdb_source": "tmdb_api"
  },
  {
    "id": "206689",
    "type": "tmdb",
    "title": "跟我说爱我",
    "posterPath": "https://image.tmdb.org/t/p/w500/ovlknh9n4NloyWOJu1pmSOYhZC4.jpg",
    "releaseDate": "2023-01-01",
    "mediaType": "tv",
    "rating": "8.0",
    "description": "「对于听不到他人脚步声的我来说，确保和他人保持安全距离是必须的，这样就不会有人受伤。」「认识你之后我才知道，就算无法说话、看不到，还是有非常多方法可以传达心意。」自幼失聪的画家车振宇已经习惯了孤独的生活，直到某一天，一位怀抱梦想的女演员郑暮恩悄悄地进入他寂静的生活。这部疗愈的经典爱情故事描绘了两人之间用手对话、用心聆听的沟通与爱情。",
    "link": null,
    "tmdb_id": "206689",
    "tmdb_site_id": "tv/206689",
    "tmdb_season_number": null,
    "tmdb_origin_countries": [
      "KR"
    ],
    "tmdb_source": "tmdb_api"
  },
  {
    "id": "215474",
    "type": "tmdb",
    "title": "单恋原声带 #2",
    "posterPath": "https://image.tmdb.org/t/p/w500/oKrdi87lFI8vDNsr1jVmyftmKBW.jpg",
    "releaseDate": "2023-01-01",
    "mediaType": "tv",
    "rating": "4.7",
    "description": "守护和贤瑞过去曾相爱六年，两人再次相遇，一位已是年轻、多金的公司首席执行官，一位则是已放弃梦想的钢琴教师。同时，拥有音乐才华的凯决定和守护一起创作，并邀请贤瑞担任演奏者。三人之间产生微妙的气氛。最后在一番波折后，守护和贤瑞复合，但他们是否又会走向相同的结局呢？",
    "link": null,
    "tmdb_id": "215474",
    "tmdb_site_id": "tv/215474",
    "tmdb_season_number": null,
    "tmdb_origin_countries": [
      "KR"
    ],
    "tmdb_source": "tmdb_api"
  },
  {
    "id": "226907",
    "type": "tmdb",
    "title": "海妖的呼唤：火之岛生存战",
    "posterPath": "https://image.tmdb.org/t/p/w500/itAOFWuejY9Xdk1XaVxPtHN7q2M.jpg",
    "releaseDate": "2023-05-30",
    "mediaType": "tv",
    "rating": "7.5",
    "description": "在一座偏远的岛屿上，24 名女警官、消防员、保镖、战士、运动员和特技演员按职业组队，为生存而战。",
    "link": null,
    "tmdb_id": "226907",
    "tmdb_site_id": "tv/226907",
    "tmdb_season_number": null,
    "tmdb_origin_countries": [
      "KR"
    ],
    "tmdb_source": "tmdb_api"
  },
  {
    "id": "202625",
    "type": "tmdb",
    "title": "神圣的偶像",
    "posterPath": "https://image.tmdb.org/t/p/w500/iqvxDOJmC7AsNPpMoIra4mV89Bc.jpg",
    "releaseDate": "2023-01-01",
    "mediaType": "tv",
    "rating": "7.3",
    "description": "来自另一个世界的伦布里，进入现实世界无名偶像禹延宇的身体，展开一段奇幻爱情故事。",
    "link": null,
    "tmdb_id": "202625",
    "tmdb_site_id": "tv/202625",
    "tmdb_season_number": null,
    "tmdb_origin_countries": [
      "KR"
    ],
    "tmdb_source": "tmdb_api"
  },
  {
    "id": "131305",
    "type": "tmdb",
    "title": "绝世网红",
    "posterPath": "https://image.tmdb.org/t/p/w500/8WY3IGk4a3PzfrncHp3Y3vtkO2y.jpg",
    "releaseDate": "2023-06-30",
    "mediaType": "tv",
    "rating": "7.8",
    "description": "名气、金钱、权力。徐雅莉一夜爆红，成为社交媒体明星。但在这个浮华光鲜的网红世界，致命的后果在等待着她。",
    "link": null,
    "tmdb_id": "131305",
    "tmdb_site_id": "tv/131305",
    "tmdb_season_number": null,
    "tmdb_origin_countries": [
      "KR"
    ],
    "tmdb_source": "tmdb_api"
  },
  {
    "id": "232812",
    "type": "tmdb",
    "title": "少年时代",
    "posterPath": "https://image.tmdb.org/t/p/w500/nuvp2IvlAXcTEeUEkDKRePYxPFZ.jpg",
    "releaseDate": "2023-01-01",
    "mediaType": "tv",
    "rating": "8.2",
    "description": "以喜剧的方式讲述了隐秘又可爱的忠清道人的故事。这是一部可以在其中感受到1980年代中后期农村高中生的日常生活和回忆中的音乐所唤起的乡愁的悬疑青春电视剧。剧中任时完饰演居住在忠清南道牙山温阳的瘦小懦弱的少年张秉泰。在学校这个小社会，属于食物链最底层的张秉泰因为父亲的关系连夜逃到隔壁小区扶余后，成为了扶余农业高中的转学生。之后他遇到了意想不到的事件，经历了反转。",
    "link": null,
    "tmdb_id": "232812",
    "tmdb_site_id": "tv/232812",
    "tmdb_season_number": null,
    "tmdb_origin_countries": [
      "KR"
    ],
    "tmdb_source": "tmdb_api"
  }
]
