[
  {
    "id": "34787",
    "type": "tmdb",
    "title": "双恋 Alternative",
    "posterPath": "https://lain.bgm.tv/r/400/pic/cover/l/38/18/2643_IiIUQ.jpg",
    "releaseDate": "2005-04-06",
    "mediaType": "tv",
    "rating": "7.5",
    "description": "13话 /  2005年4月6日 / 平尾隆之（チーフディレクター） / 双葉ひな、ささきむつみ / 小林利充",
    "link": null,
    "tmdb_id": "34787",
    "tmdb_site_id": "tv/34787",
    "tmdb_season_number": null,
    "tmdb_origin_countries": [],
    "tmdb_source": "bangumi_data"
  },
  {
    "id": "46025",
    "type": "tmdb",
    "title": "IS〈无限斯特拉托斯〉",
    "posterPath": "https://lain.bgm.tv/r/400/pic/cover/l/0f/bc/9800_eIkZW.jpg",
    "releaseDate": "2011-01-06",
    "mediaType": "tv",
    "rating": "6.1",
    "description": "12话 /  2011年1月6日 / 菊地康仁 / 弓弦イズル（MF文庫J／メディアファクトリー刊） / 倉嶋丈康",
    "link": null,
    "tmdb_id": "46025",
    "tmdb_site_id": "tv/46025",
    "tmdb_season_number": null,
    "tmdb_origin_countries": [],
    "tmdb_source": "bangumi_data"
  },
  {
    "id": "61440",
    "type": "tmdb",
    "title": "噬血狂袭",
    "posterPath": "https://lain.bgm.tv/r/400/pic/cover/l/c0/f7/67826_oa7Xa.jpg",
    "releaseDate": "2013-10-04",
    "mediaType": "tv",
    "rating": "6.6",
    "description": "24话 /  2013年10月4日 / 山本秀世 / 三雲岳斗（電撃文庫/株式会社KADOKAWA アスキー・メディアワークス刊） / 佐野恵一",
    "link": null,
    "tmdb_id": "61440",
    "tmdb_site_id": "tv/61440",
    "tmdb_season_number": null,
    "tmdb_origin_countries": [],
    "tmdb_source": "bangumi_data"
  },
  {
    "id": "260523",
    "type": "tmdb",
    "title": "摇滚乃是淑女的爱好",
    "posterPath": "https://lain.bgm.tv/r/400/pic/cover/l/c4/b5/504678_iCezc.jpg",
    "releaseDate": "2025-04-03",
    "mediaType": "tv",
    "rating": "6.2",
    "description": "13话 /  2025年4月3日 / 綿田慎也 / 福田宏「ロックは淑女の嗜みでして」（白泉社「ヤングアニマル」連載） / 宮谷里沙",
    "link": null,
    "tmdb_id": "260523",
    "tmdb_site_id": "tv/260523",
    "tmdb_season_number": null,
    "tmdb_origin_countries": [],
    "tmdb_source": "bangumi_data"
  },
  {
    "id": "93377",
    "type": "link",
    "title": "瑞克和莫蒂 第一季",
    "posterPath": "https://lain.bgm.tv/r/400/pic/cover/l/db/e4/93377_TEzAK.jpg",
    "releaseDate": "2013-12-02",
    "mediaType": "anime",
    "rating": "8.4",
    "description": "11话 /  2013年12月2日 / Justin Roiland、Dan Harmon",
    "link": "https://bgm.tv/subject/93377"
  },
  {
    "id": "63576",
    "type": "tmdb",
    "title": "Fate/kaleid liner 魔法少女☆伊莉雅 2wei Herz!",
    "posterPath": "https://lain.bgm.tv/r/400/pic/cover/l/0f/31/113134_NkaCg.jpg",
    "releaseDate": "2015-07-24",
    "mediaType": "tv",
    "rating": "7.1",
    "description": "10话 /  2015年7月24日 / 神保昌登 / ひろやまひろし・TYPE-MOON / 牛島希",
    "link": null,
    "tmdb_id": "63576",
    "tmdb_site_id": "tv/63576/season/3",
    "tmdb_season_number": 3,
    "tmdb_origin_countries": [],
    "tmdb_source": "bangumi_data"
  },
  {
    "id": "30980",
    "type": "tmdb",
    "title": "魔法禁书目录 第二季",
    "posterPath": "https://lain.bgm.tv/r/400/pic/cover/l/8d/91/7843_KPkpp.jpg",
    "releaseDate": "2010-10-08",
    "mediaType": "tv",
    "rating": "6.7",
    "description": "24话 /  2010年10月8日 / 錦織博 / 鎌池和馬（電撃文庫刊） / 田中雄一",
    "link": null,
    "tmdb_id": "30980",
    "tmdb_site_id": "tv/30980/season/2",
    "tmdb_season_number": 2,
    "tmdb_origin_countries": [],
    "tmdb_source": "bangumi_data"
  },
  {
    "id": "80563",
    "type": "tmdb",
    "title": "异世界魔王与召唤少女的奴隶魔术",
    "posterPath": "https://lain.bgm.tv/r/400/pic/cover/l/53/20/236224_OcW1t.jpg",
    "releaseDate": "2018-07-05",
    "mediaType": "tv",
    "rating": "5.9",
    "description": "12话 /  2018年7月5日 / 村野佑太 / むらさきゆきや（講談社ラノベ文庫刊） / 金子志津枝",
    "link": null,
    "tmdb_id": "80563",
    "tmdb_site_id": "tv/80563",
    "tmdb_season_number": null,
    "tmdb_origin_countries": [],
    "tmdb_source": "bangumi_data"
  },
  {
    "id": "120155",
    "type": "tmdb",
    "title": "史上最强的大魔王转生为村民A",
    "posterPath": "https://lain.bgm.tv/r/400/pic/cover/l/22/3c/330055_AHxG5.jpg",
    "releaseDate": "2022-04-06",
    "mediaType": "tv",
    "rating": "4.7",
    "description": "12话 /  2022年4月6日 / 湊未來 / 下等妙人（株式会社KADOKAWA／ファンタジア文庫刊） / 野口孝行",
    "link": null,
    "tmdb_id": "120155",
    "tmdb_site_id": "tv/120155",
    "tmdb_season_number": null,
    "tmdb_origin_countries": [],
    "tmdb_source": "bangumi_data"
  },
  {
    "id": "113137",
    "type": "tmdb",
    "title": "女友成堆 第二季",
    "posterPath": "https://lain.bgm.tv/r/400/pic/cover/l/da/2f/398949_y6u1X.jpg",
    "releaseDate": "2023-10-06",
    "mediaType": "tv",
    "rating": "6.5",
    "description": "12话 /  2023年10月6日 / 鈴木孝聡 / ヒロユキ（講談社「週刊少年マガジン」連載） / 萩原しょう子",
    "link": null,
    "tmdb_id": "113137",
    "tmdb_site_id": "tv/113137/season/2",
    "tmdb_season_number": 2,
    "tmdb_origin_countries": [],
    "tmdb_source": "bangumi_data"
  },
  {
    "id": "258912",
    "type": "tmdb",
    "title": "魔法制造者 ～异世界魔法的制作方法～",
    "posterPath": "https://lain.bgm.tv/r/400/pic/cover/l/00/da/503268_SdLDD.jpg",
    "releaseDate": "2025-01-08",
    "mediaType": "tv",
    "rating": "5.6",
    "description": "12话 /  2025年1月8日 / 古賀一臣 / 鏑木カヅキ「マジック・メイカー -異世界魔法の作り方-」（MFブックス） / 野口孝行",
    "link": null,
    "tmdb_id": "258912",
    "tmdb_site_id": "tv/258912",
    "tmdb_season_number": null,
    "tmdb_origin_countries": [],
    "tmdb_source": "bangumi_data"
  },
  {
    "id": "74098",
    "type": "tmdb",
    "title": "此花绮谭",
    "posterPath": "https://lain.bgm.tv/r/400/pic/cover/l/ab/fd/211934_HHeOH.jpg",
    "releaseDate": "2017-10-04",
    "mediaType": "tv",
    "rating": "7.5",
    "description": "12话 /  2017年10月4日 / 岡本英樹 / 天乃咲哉（月刊バーズ・幻冬舎コミックス刊） / 黒澤桂子",
    "link": null,
    "tmdb_id": "74098",
    "tmdb_site_id": "tv/74098",
    "tmdb_season_number": null,
    "tmdb_origin_countries": [],
    "tmdb_source": "bangumi_data"
  },
  {
    "id": "129195",
    "type": "tmdb",
    "title": "异世界药局",
    "posterPath": "https://lain.bgm.tv/r/400/pic/cover/l/05/43/342200_2hdHa.jpg",
    "releaseDate": "2022-07-10",
    "mediaType": "tv",
    "rating": "6.1",
    "description": "12话 /  2022年7月10日 / 草川啓造 / 高山理図（MFブックス／KADOKAWA刊） / 松本麻友子",
    "link": null,
    "tmdb_id": "129195",
    "tmdb_site_id": "tv/129195",
    "tmdb_season_number": null,
    "tmdb_origin_countries": [],
    "tmdb_source": "bangumi_data"
  },
  {
    "id": "27660",
    "type": "tmdb",
    "title": "银河英雄传说",
    "posterPath": "https://lain.bgm.tv/r/400/pic/cover/l/c7/55/2907_8xX82.jpg",
    "releaseDate": "1988-01-08",
    "mediaType": "tv",
    "rating": "8.7",
    "description": "110话 /  1988年1月8日 / 田中芳樹 / 本木久年(1期)、清水恵蔵(1期、3期～4期)、久米一成(2期)",
    "link": null,
    "tmdb_id": "27660",
    "tmdb_site_id": "tv/27660",
    "tmdb_season_number": null,
    "tmdb_origin_countries": [],
    "tmdb_source": "bangumi_data"
  },
  {
    "id": "12609",
    "type": "tmdb",
    "title": "龙珠",
    "posterPath": "https://lain.bgm.tv/r/400/pic/cover/l/84/45/9565_s98m3.jpg",
    "releaseDate": "1986-02-26",
    "mediaType": "tv",
    "rating": "8.2",
    "description": "153话 /  1986年2月26日 / 鳥山明（集英社「週刊少年ジャンプ」連載）",
    "link": null,
    "tmdb_id": "12609",
    "tmdb_site_id": "tv/12609",
    "tmdb_season_number": null,
    "tmdb_origin_countries": [],
    "tmdb_source": "bangumi_data"
  },
  {
    "id": "83095",
    "type": "tmdb",
    "title": "盾之勇者成名录 第四季",
    "posterPath": "https://lain.bgm.tv/r/400/pic/cover/l/64/b6/476542_lV2ie.jpg",
    "releaseDate": "2025-07-09",
    "mediaType": "tv",
    "rating": "5.2",
    "description": "12话 /  2025年7月9日 / 垪和等 / アネコユサギ（MFブックス「盾の勇者の成り上がり」KADOKAWA刊） / Franziska van Wulfen、小松沙奈、諏訪真弘；人设协力：滝口弘喜",
    "link": null,
    "tmdb_id": "83095",
    "tmdb_site_id": "tv/83095/season/4",
    "tmdb_season_number": 4,
    "tmdb_origin_countries": [],
    "tmdb_source": "bangumi_data"
  },
  {
    "id": "30982",
    "type": "tmdb",
    "title": "棋魂",
    "posterPath": "https://lain.bgm.tv/r/400/pic/cover/l/c3/61/605_Jg0W8.jpg",
    "releaseDate": "2001-10-10",
    "mediaType": "tv",
    "rating": "8.3",
    "description": "75话 /  2001年10月10日 / 西澤晋（1～15）、神谷純（16～59）、えんどうてつや（57～75） / ほったゆみ、小畑健(集英社「週刊少年ジャンプ」連載) / アニメーションキャラクターデザイン→メインキャラクターデザイン：本橋秀之〔途中から〕//キャラクターデザイン　関口可奈味、上田美由紀、芝美奈子",
    "link": null,
    "tmdb_id": "30982",
    "tmdb_site_id": "tv/30982",
    "tmdb_season_number": null,
    "tmdb_origin_countries": [],
    "tmdb_source": "bangumi_data"
  },
  {
    "id": "21750",
    "type": "tmdb",
    "title": "东之伊甸",
    "posterPath": "https://lain.bgm.tv/r/400/pic/cover/l/80/a8/1451_uU8k9.jpg",
    "releaseDate": "2009-04-09",
    "mediaType": "tv",
    "rating": "7.5",
    "description": "11话 /  2009年4月9日 / 神山健治 / 神山健治 / 森川聡子",
    "link": null,
    "tmdb_id": "21750",
    "tmdb_site_id": "tv/21750",
    "tmdb_season_number": null,
    "tmdb_origin_countries": [],
    "tmdb_source": "bangumi_data"
  },
  {
    "id": "253007",
    "type": "tmdb",
    "title": "亲吻姐姐OAD",
    "posterPath": "https://lain.bgm.tv/r/400/pic/cover/l/82/b0/3359_56C6d.jpg",
    "releaseDate": "2008-12-22",
    "mediaType": "tv",
    "rating": "6.9",
    "description": "12话 /  2008年12月22日 / 名和宗則 / ぢたま某（掲載「月刊ヤングマガジン」講談社刊） / 下谷智之",
    "link": null,
    "tmdb_id": "253007",
    "tmdb_site_id": "tv/253007",
    "tmdb_season_number": null,
    "tmdb_origin_countries": [],
    "tmdb_source": "bangumi_data"
  },
  {
    "id": "99618",
    "type": "tmdb",
    "title": "转生成蜘蛛又怎样！",
    "posterPath": "https://lain.bgm.tv/r/400/pic/cover/l/83/73/252782_aWyEn.jpg",
    "releaseDate": "2021-01-08",
    "mediaType": "tv",
    "rating": "6.0",
    "description": "24话 /  2021年1月8日 / 板垣伸 / 馬場翁『蜘蛛ですが、なにか？』（カドカワBOOKS刊） / 田中紀衣",
    "link": null,
    "tmdb_id": "99618",
    "tmdb_site_id": "tv/99618",
    "tmdb_season_number": null,
    "tmdb_origin_countries": [],
    "tmdb_source": "bangumi_data"
  },
  {
    "id": "116724",
    "type": "tmdb",
    "title": "白沙的水族馆",
    "posterPath": "https://lain.bgm.tv/r/400/pic/cover/l/d4/a3/325281_CZa9A.jpg",
    "releaseDate": "2021-07-08",
    "mediaType": "tv",
    "rating": "6.6",
    "description": "24话 /  2021年7月8日 / 篠原俊哉 / project ティンガーラ / 秋山有希",
    "link": null,
    "tmdb_id": "116724",
    "tmdb_site_id": "tv/116724",
    "tmdb_season_number": null,
    "tmdb_origin_countries": [],
    "tmdb_source": "bangumi_data"
  },
  {
    "id": "58237",
    "type": "tmdb",
    "title": "银之匙 Silver Spoon",
    "posterPath": "https://lain.bgm.tv/r/400/pic/cover/l/3a/0d/59664_xK3y7.jpg",
    "releaseDate": "2013-07-11",
    "mediaType": "tv",
    "rating": "7.9",
    "description": "11话 /  2013年7月11日 / 伊藤智彦 / 荒川弘「銀の匙 Silver Spoon」（小学館「週刊少年サンデー」連載） / 中井準",
    "link": null,
    "tmdb_id": "58237",
    "tmdb_site_id": "tv/58237",
    "tmdb_season_number": null,
    "tmdb_origin_countries": [],
    "tmdb_source": "bangumi_data"
  },
  {
    "id": "348240",
    "type": "link",
    "title": "凡人修仙传 年番",
    "posterPath": "https://lain.bgm.tv/r/400/pic/cover/l/81/b6/348240_ODGGg.jpg",
    "releaseDate": "2021-11-14",
    "mediaType": "anime",
    "rating": "7.4",
    "description": "51话 /  2021年11月14日 / 王裕仁、伍镇焯、赵侠 / 忘语",
    "link": "https://bgm.tv/subject/348240"
  },
  {
    "id": "250598",
    "type": "tmdb",
    "title": "大叔新人冒险者，被最强小队往死里锻炼后变无敌了",
    "posterPath": "https://lain.bgm.tv/r/400/pic/cover/l/6a/45/427059_1V5vV.jpg",
    "releaseDate": "2024-07-01",
    "mediaType": "tv",
    "rating": "5.6",
    "description": "12话 /  2024年7月1日 / 片貝慎 / 岸馬きらく（HJノベルス／ホビージャパン）；漫画：荻野ケン（コミックファイア連載／HJコミックス） / 江口麻里；副：江古田ノイヅ、中島駿、鈴木陽子",
    "link": null,
    "tmdb_id": "250598",
    "tmdb_site_id": "tv/250598",
    "tmdb_season_number": null,
    "tmdb_origin_countries": [],
    "tmdb_source": "bangumi_data"
  }
]
