[
  {
    "id": "592522",
    "type": "link",
    "title": "테라리움 어드벤처",
    "posterPath": "https://lain.bgm.tv/r/400/pic/cover/l/42/66/592522_n30bg.jpg",
    "releaseDate": "2023-05-31",
    "mediaType": "anime",
    "rating": "",
    "description": "3话 /  2023年5月31日 / 빛무리",
    "link": "https://bgm.tv/subject/592522"
  },
  {
    "id": "596462",
    "type": "link",
    "title": "鬼太郎：河童的火星改造",
    "posterPath": "https://lain.bgm.tv/r/400/pic/cover/l/d8/8d/596462_pW7rI.jpg",
    "releaseDate": "2023-09-15",
    "mediaType": "anime",
    "rating": "",
    "description": "1话 /  2023年9月15日",
    "link": "https://bgm.tv/subject/596462"
  },
  {
    "id": "608961",
    "type": "link",
    "title": "樱桃小丸子 被南十字星迷住",
    "posterPath": "https://lain.bgm.tv/r/400/pic/cover/l/67/52/608961_1p8oQ.jpg",
    "releaseDate": "2023-03-24",
    "mediaType": "anime",
    "rating": "",
    "description": "1话 /  2023年3月24日",
    "link": "https://bgm.tv/subject/608961"
  },
  {
    "id": "609113",
    "type": "link",
    "title": "猴子扳手",
    "posterPath": "https://lain.bgm.tv/r/400/pic/cover/l/57/12/609113_rR66S.jpg",
    "releaseDate": "2023-06-24",
    "mediaType": "anime",
    "rating": "",
    "description": "2023年6月24日",
    "link": "https://bgm.tv/subject/609113"
  },
  {
    "id": "612411",
    "type": "link",
    "title": "炼气练了三千年 动态漫 第三季",
    "posterPath": "https://lain.bgm.tv/r/400/pic/cover/l/a6/f1/612411_kAKkm.jpg",
    "releaseDate": "2023-01-01",
    "mediaType": "anime",
    "rating": "",
    "description": "100话 /  2023 年 4 月 5 日 / 兰桂玮",
    "link": "https://bgm.tv/subject/612411"
  },
  {
    "id": "615092",
    "type": "link",
    "title": "发光的河",
    "posterPath": "https://lain.bgm.tv/r/400/pic/cover/l/aa/f3/615092_5OBFU.jpg",
    "releaseDate": "2023-01-01",
    "mediaType": "anime",
    "rating": "",
    "description": "2023-02-19 / 雷磊",
    "link": "https://bgm.tv/subject/615092"
  },
  {
    "id": "615228",
    "type": "link",
    "title": "神秘公寓：幽灵球 ZERO",
    "posterPath": "https://lain.bgm.tv/r/400/pic/cover/l/18/a2/615228_dr9UC.jpg",
    "releaseDate": "2023-03-30",
    "mediaType": "anime",
    "rating": "",
    "description": "11话 /  2023年3月30日 / 박홍근",
    "link": "https://bgm.tv/subject/615228"
  },
  {
    "id": "615230",
    "type": "link",
    "title": "神秘公寓：幽灵球 ZERO 第二个故事",
    "posterPath": "https://lain.bgm.tv/r/400/pic/cover/l/ad/c3/615230_3lUpP.jpg",
    "releaseDate": "2023-11-30",
    "mediaType": "anime",
    "rating": "",
    "description": "15话 /  2023年11月30日 / 박홍근",
    "link": "https://bgm.tv/subject/615230"
  },
  {
    "id": "615232",
    "type": "link",
    "title": "神秘公寓特别篇：朝鲜退魔实录",
    "posterPath": "https://lain.bgm.tv/r/400/pic/cover/l/be/d4/615232_mrtr7.jpg",
    "releaseDate": "2023-07-14",
    "mediaType": "anime",
    "rating": "",
    "description": "4话 /  2023年7月14日 / 양광석",
    "link": "https://bgm.tv/subject/615232"
  },
  {
    "id": "616229",
    "type": "link",
    "title": "小怪兽成长日记 未来预报",
    "posterPath": "https://lain.bgm.tv/r/400/pic/cover/l/62/9e/616229_rZrw9.jpg",
    "releaseDate": "2023-12-21",
    "mediaType": "anime",
    "rating": "",
    "description": "5话 /  2023年12月21日",
    "link": "https://bgm.tv/subject/616229"
  },
  {
    "id": "616308",
    "type": "link",
    "title": "节气小精灵",
    "posterPath": "https://lain.bgm.tv/r/400/pic/cover/l/28/22/616308_zn1Z9.jpg",
    "releaseDate": "2023-08-17",
    "mediaType": "anime",
    "rating": "",
    "description": "52话 /  2023年8月17日",
    "link": "https://bgm.tv/subject/616308"
  },
  {
    "id": "225829",
    "type": "tmdb",
    "title": "100% Wolf: The Book of Hath",
    "posterPath": "https://image.tmdb.org/t/p/w500/Ac8RBBvN2sZbADha04EsfdjsWil.jpg",
    "releaseDate": "2023-05-01",
    "mediaType": "tv",
    "rating": "7.0",
    "description": "26话 /  2023年5月1日",
    "link": null,
    "tmdb_id": "225829",
    "tmdb_site_id": "tv/225829",
    "tmdb_season_number": null,
    "tmdb_origin_countries": [
      "AU"
    ],
    "tmdb_source": "tmdb_api"
  },
  {
    "id": "625397",
    "type": "link",
    "title": "毛毛镇之海洋大发现",
    "posterPath": "https://lain.bgm.tv/r/400/pic/cover/l/7d/3b/625397_ZXUvu.jpg",
    "releaseDate": "2023-07-03",
    "mediaType": "anime",
    "rating": "",
    "description": "52话 /  2023年7月3日",
    "link": "https://bgm.tv/subject/625397"
  },
  {
    "id": "626072",
    "type": "link",
    "title": "故宫里的大怪兽之莫奈何的谜题",
    "posterPath": "https://lain.bgm.tv/r/400/pic/cover/l/17/98/626072_0BmGf.jpg",
    "releaseDate": "2023-07-05",
    "mediaType": "anime",
    "rating": "",
    "description": "26话 /  2023年7月5日 / 动画部分：沈琰、黎明；实拍部分：骆芊竹 / 常怡 / 刘晴川、林紫祺、赵梓欣、任梦悦",
    "link": "https://bgm.tv/subject/626072"
  },
  {
    "id": "629649",
    "type": "link",
    "title": "天眼之父南仁东",
    "posterPath": "https://lain.bgm.tv/r/400/pic/cover/l/08/3c/629649_pIKKn.jpg",
    "releaseDate": "2023-01-01",
    "mediaType": "anime",
    "rating": "",
    "description": "10话 /  2023-12-26",
    "link": "https://bgm.tv/subject/629649"
  },
  {
    "id": "630111",
    "type": "link",
    "title": "魔法舒舒",
    "posterPath": "https://lain.bgm.tv/r/400/pic/cover/l/80/d8/630111_T76wV.jpg",
    "releaseDate": "2023-01-01",
    "mediaType": "anime",
    "rating": "",
    "description": "26话 /  2023（俄罗斯）",
    "link": "https://bgm.tv/subject/630111"
  },
  {
    "id": "630372",
    "type": "link",
    "title": "好伙伴",
    "posterPath": "https://lain.bgm.tv/r/400/pic/cover/l/3e/28/630372_J418Z.jpg",
    "releaseDate": "2023-01-01",
    "mediaType": "anime",
    "rating": "",
    "description": "8话 /  2023-12-20",
    "link": "https://bgm.tv/subject/630372"
  },
  {
    "id": "630481",
    "type": "link",
    "title": "喜多多与乖宝宝",
    "posterPath": "https://lain.bgm.tv/r/400/pic/cover/l/3e/e7/630481_tv4u4.jpg",
    "releaseDate": "2023-01-01",
    "mediaType": "anime",
    "rating": "",
    "description": "60话 /  2023 / 马千",
    "link": "https://bgm.tv/subject/630481"
  },
  {
    "id": "631049",
    "type": "link",
    "title": "米妮欢乐屋：一起来露营",
    "posterPath": "https://lain.bgm.tv/r/400/pic/cover/l/98/c6/631049_vVj3g.jpg",
    "releaseDate": "2023-06-21",
    "mediaType": "anime",
    "rating": "",
    "description": "20话 /  2023年6月21日",
    "link": "https://bgm.tv/subject/631049"
  },
  {
    "id": "633707",
    "type": "link",
    "title": "魔法甜心 奇妙! 萌可",
    "posterPath": "https://lain.bgm.tv/r/400/pic/cover/l/80/c6/633707_io13v.jpg",
    "releaseDate": "2023-09-22",
    "mediaType": "anime",
    "rating": "",
    "description": "26话 /  2023年9月22日",
    "link": "https://bgm.tv/subject/633707"
  },
  {
    "id": "636043",
    "type": "link",
    "title": "おじゃる丸 第26シリーズ",
    "posterPath": "https://lain.bgm.tv/r/400/pic/cover/l/04/7f/636043_ZtLII.jpg",
    "releaseDate": "2023-04-03",
    "mediaType": "anime",
    "rating": "",
    "description": "60话 /  2023年4月3日",
    "link": "https://bgm.tv/subject/636043"
  },
  {
    "id": "639051",
    "type": "link",
    "title": "ELEMON",
    "posterPath": "https://lain.bgm.tv/r/400/pic/cover/l/96/ad/639051_7YqkQ.jpg",
    "releaseDate": "2023-09-29",
    "mediaType": "anime",
    "rating": "",
    "description": "29话 /  2023年9月29日",
    "link": "https://bgm.tv/subject/639051"
  },
  {
    "id": "640924",
    "type": "link",
    "title": "海底小纵队 第8季",
    "posterPath": "https://lain.bgm.tv/r/400/pic/cover/l/d7/34/640924_ZT93I.jpg",
    "releaseDate": "2023-01-01",
    "mediaType": "anime",
    "rating": "",
    "description": "26话 /  2023-05-26 / 韩翔",
    "link": "https://bgm.tv/subject/640924"
  },
  {
    "id": "643615",
    "type": "link",
    "title": "悼歌",
    "posterPath": "https://lain.bgm.tv/r/400/pic/cover/l/1e/e2/643615_WqqPl.jpg",
    "releaseDate": "2023-11-20",
    "mediaType": "anime",
    "rating": "",
    "description": "2023年11月20日 / Hadrien Maton",
    "link": "https://bgm.tv/subject/643615"
  }
]
